Workbook

Sheet Template RSL
A1: TENDÊNCIAS E DESAFIOS EM SI - ESTRUTURAÇÃO DA INVESTIGAÇÃO SISTEMÁTICA | Y1: //
A2: Parte 1: Planejamento | C2: Comentários do professor
A3: Integrantes do time: | B3: Luiza Trigueiro, Giovanna Clócate, Antonio Carolino, Beatriz Mergulhão, Mateus Ribeiro, Luiz Miguel Gonzaga | Y3: //////////////////////////////////////
A4: Tema de pesquisa: | B4: Desenvolvimento e uso de agentes de IA para tomada de decisão e automação em operações de atendimento ao cliente (triagem e roteamento de tickets, resposta assistida/copilot, priorização por SLA, escalonamento, sumarização e registro no CRM, QA/compliance de conversas e pós-atendimento (NPS/retensão)), considerando técnicas (LLMs, MAS, RL), processo de desenvolvimento e personalização por políticas e segmentos. | Y4: /
A5: Objetivos da pesquisa: | B5: 1. Analisar a eficácia da implementação de agentes de IA em processos de tomada de decisão e automação de tarefas em organizações de médio porte. 2. Investigar como os agentes de IA impactam a estrutura de trabalho, considerando requalificação de colaboradores, produtividade e integração tecnológica. 3. Propor diretrizes e boas práticas para o desenvolvimento e adoção de agentes de IA de forma ética, eficiente e personalizada.
A6: Motivação/Justificativa: | B6: 1. Agentes de IA são cruciais para a otimização de custos, aumento da velocidade e precisão na tomada de decisão, e para a liberação de colaboradores para tarefas mais estratégicas. 2. O uso de IA em organizações levanta questões complexas, como a confiabilidade dos agentes (o problema da "caixa-preta"), a necessidade de ética e compliance nos processos automatizados, e o desafio da integração com sistemas legados. Sua pesquisa pode ajudar a mitigar esses riscos. 3. O mercado precisa de diretrizes práticas sobre como migrar do piloto de IA para a implementação em escala (em toda a organização) de forma eficaz. Seus resultados podem fornecer insights valiosos sobre melhores práticas, ferramentas ou estratégias de gestão dessa tecnologia.
A7: Artigos referência (título e link): | B7: Artificial Intelligence in Decision-making: Literature Review ( https://www.researchgate.net/publication/389628330_Artificial_Intelligence_in_Decision-making_Literature_Review?enrichId=rgreq-006d8c151c452875c7f4ea9c2f54702f-XXX&enrichSource=Y292ZXJQYWdlOzM4OTYyODMzMDtBUzoxMTQzMTI4MTMxNDI4MTkxNkAxNzQxMjk0Nzc4ODM5&el=1_x_3 ) , Nazmiye Guler, Samuel N. Kirshner, Richard Vidgen, A literature review of artificial intelligence research in business and management using machine learning and ChatGPT, Data and Information Management, Volume 8, Issue 3, 2024, 100076, ISSN 2543-9251, https://doi.org/10.1016/j.dim.2024.100076. (https://www.sciencedirect.com/science/article/pii/S2543925124000123) Autonomous AI Agents Transforming Enterprise Operations: From Static Automation to Intelligent Decision-Making Systems Maurya Priyadarshi Manipal Institute of Technology, Manipal University, India https://sarcouncil.com/download-article/SJMD-199-2025-863-870.pdf
A8: Título e link da 1 revisão selecionada | B8: Artificial Intelligence in Decision-making: Literature Review ( https://www.researchgate.net/publication/389628330_Artificial_Intelligence_in_Decision-making_Literature_Review?enrichId=rgreq-006d8c151c452875c7f4ea9c2f54702f-XXX&enrichSource=Y292ZXJQYWdlOzM4OTYyODMzMDtBUzoxMTQzMTI4MTMxNDI4MTkxNkAxNzQxMjk0Nzc4ODM5&el=1_x_3 ) Semelhanças: O foco central de ambas é o uso de agentes de IA para tomada de decisão, focando na otimização de processos e aumento da eficiência. Diferenças: O artigo se concentra mais em uma visão geral dos impactos da IA em várias áreas de tomada de decisão, analisando esse aspecto de forma mais ampla, enquanto a proposta do grupo foca especificamente nas organizações de médio porte e nos desafios da automação de tarefas repetitivas por agentes de IA
A10: Título e link da 2 revisão selecionada | B10: Quais as semelhanças e diferenças da 2 revisão com a revisão a ser desenvolvida pelo grupo? A literature review of artificial intelligence research in business and management using machine learning and ChatGPT Nazmiye Guler, Samuel N. Kirshner * University of New South Wales Business School, Sydney, 2052, Australia Richard Vidgen University of New South Wales Business School, Sydney, 2052, Australia University of Hull, School of Management, Hull, HU6 7RX, UK https://www.sciencedirect.com/science/article/pii/S2543925124000123 Semelhanças: Ambos os artigos abordam a aplicação de inteligência artificial em contextos organizacionais, com foco em autonomia e tomada de decisão. Ambos reconhecem o impacto potencial da IA em otimizar operações e aumentar a eficiência, e discutem a necessidade de estruturas de governança para garantir a eficácia e segurança no uso de IA. Ambos também lidam com avanços tecnológicos, como modelos de linguagem, no desenvolvimento de sistemas de IA autônomos. Diferenças: O artigo de Priyadarshi foca especificamente em agentes de IA autônomos, detalhando como eles evoluem da automação estática para sistemas inteligentes de tomada de decisão, com arquiteturas complexas e exemplos práticos em diversas áreas de operação empresarial. Já o artigo sobre AI em pesquisa de negócios e gestão utiliza técnicas de aprendizado de máquina para realizar revisões de literatura computacionais, abordando temas amplos como impacto da IA nas organizações e utilizando ferramentas como o ChatGPT para análise e rotulação de tópicos em grandes volumes de pesquisa. Essa comparação pode ajudar a destacar os aspectos práticos de implementação de IA no artigo de Priyadarshi, enquanto o artigo de Guler et al. oferece uma visão macro sobre como as tecnologias de IA estão sendo exploradas na literatura de negócios e gestão.
A11: Título e link da 3 revisão selecionada | B11: Quais as semelhanças e diferenças da 3 revisão com a revisão a ser desenvolvida pelo grupo? Autonomous AI Agents Transforming Enterprise Operations: From Static Automation to Intelligent Decision-Making Systems Maurya Priyadarshi Manipal Institute of Technology, Manipal University, India https://sarcouncil.com/download-article/SJMD-199-2025-863-870.pdf Semelhanças: Tanto a revisão de Priyadarshi (2025) quanto a pesquisa do grupo tratam do uso de agentes de IA para automação de tarefas e tomada de decisão em organizações, destacando ganhos de eficiência, redução de custos e aumento da produtividade, além de reconhecerem desafios como confiabilidade, segurança, compliance e impactos no trabalho humano. No entanto, enquanto o artigo internacional tem um foco mais técnico e abrangente, detalhando arquiteturas, frameworks (como LangChain, Microsoft Copilot e Relevance AI) e múltiplos casos práticos em áreas como atendimento ao cliente, operações de TI e vendas, a revisão do grupo concentra-se em organizações de médio porte, analisando a eficácia e os desafios da implementação de agentes de IA especificamente em tarefas repetitivas e propondo metodologias de adoção. Assim, enquanto o artigo mapeia estratégias globais e ferramentas de larga escala, a pesquisa do grupo se dedica mais aos impactos organizacionais, à realocação de pessoas e às diretrizes de uso em contextos mais restritos.
A12: Questão central de pesquisa: | B12: Como a implementação de agentes de IA em operações de atendimento ao cliente pode melhorar a eficiência, a produtividade e a qualidade do serviço em organizações de médio porte, considerando os desafios de integração tecnológica, as mudanças na estrutura de trabalho e os impactos na experiência dos colaboradores e dos clientes?
A13: Questões secundárias: | B13: Como os agentes de IA influenciam a alocação e redistribuição de tarefas em equipes de atendimento ao cliente, e de que forma isso afeta a gestão de pessoal nas organizações de médio porte? Quais são as implicações éticas e operacionais do uso de agentes de IA para automação de decisões e interações com clientes, e como essas questões podem ser monitoradas e mitigadas? Como a adoção de agentes de IA altera as competências e habilidades exigidas dos colaboradores em operações de atendimento, especialmente em relação à interpretação, supervisão e colaboração com sistemas autônomos?
A14: Método: | B14: Revisão sistemática
A15: RESULTADO ESPERADO PARTE 1: | B15: Planejamento da pesquisa, definindo tema, objetivos, motivação, questões de pesquisa, fundamentados por ao menos 3 artigos de referência.
E51: /

Sheet Página28

Sheet Fontes de pesquisa
A2: Principais Bases de Pesquisa
A4: Scopus | B4: Tutorial Scopus - Busca Avançada: https://www.youtube.com/watch?v=tmchre5JjFA
B5: Exemplo simples de busca avançada: https://www.youtube.com/watch?v=MdUadNWrS_8
A7: ACM | B7: Navegando na ACM Library: https://www.youtube.com/watch?v=zUHF4w-6nhc
B8: Exemplo simples de busca avançada: https://www.youtube.com/watch?v=_QtrHrHOlFg
A10: IEEE | B10: Tutorial IEEExplore for RSL - https://www.youtube.com/watch?v=_i6vIjHGh0I
B11: Exemplo simples de busca avançada: https://www.youtube.com/watch?v=C-LXhuLCZdQ
A13: Outras bases: Springer, Science Direct, Emerald, AIS

Sheet Exemplo 1 - Total Experience
A1: TENDÊNCIAS E DESAFIOS EM SI - ESTRUTURAÇÃO DA INVESTIGAÇÃO SISTEMÁTICA
A2: Parte 1: Planejamento
A3: Integrantes do time:
A4: Tema de pesquisa: | B4: Total experience e o impacto em como os produtos/serviços estão sendo construídos
A5: Objetivos da pesquisa: | B5: Entender os impactos do total experience nos serviços/produtos ao longo do tempo Entender quais são as principais aplicações do total experience em casos reais
A6: Motivação/Justificativa: | B6: Tendência estratégica do ano de 2021 (Gartner) Mudanças dos produtos e serviços no pós-pandemia Há uma mudança gradual do consumo de commodities, que além de bens/serviços, são vistos como experiências. A quarta onda na progressão econômica trouxe o surgimento de uma nova economia: “A economia da experiência” (Jain et al., 2016, Journal of Service Theory and Practice, Vol. 27 Issue: 3, p. 642) Essencial para a sobrevivência no competitivo ambiente de e-commerce de hoje, onde o concorrente é apenas um clique de distância; Significa que as empresas precisam encontrar maneiras de oferecer aos clientes uma experiência única, muito mais do que preços baixos (BILGIHAN, 2016, International Journal of Quality and Service Sciences p. 102)
A7: Artigos referência (título e link): | B7: Client-led Design: A Systemic Approach to Information Systems Definition e-Government information systems: Evaluation-led design for public value and client trust Managing the Total Customer Experience Small business digital transformation in the context of the pandemic Impact of customer experience on loyalty a multichannel examination Customer experience – a review and research agenda Towards a unified customer experience in online shopping environments Customer experience management in hospitality: a literature synthesis, new understanding, and research agenda
A8: Questão central de pesquisa: | B8: Total experience: Como o design dirigido ao cliente está impactando os processos dos produtos/serviços no varejo online?
A9: Questões secundárias: | B9: Q1 - O estudo define os componentes do total experience? Se sim, como? Q2 - Como total experience é aplicada nas organizações atuais? Q3 - Quais são os principais impactos(Pessoas, tecnologias e processos) da total experience nos serviços/produtos, de acordo com os estudos encontrados? Q4 - Qual são as principais funções que as mídias sociais oferecem para a total experience?
A10: Método: | B10: Revisão
A11: RESULTADO ESPERADO PARTE 1: | B11: Planejamento da pesquisa, definindo tema, objetivos, motivação, questões de pesquisa, fundamentados por ao menos 2 artigos de referência.
A12: Parte 2: Protocolo de Pesquisa
A13: Palavras-chave: | B13: total experience, online retail, customer
A14: Sinônimos por palavras-chave: | B14: total experience or multiexperience or user experience or customer experience , online retail or e-commerce or eletronic commerce, customer or client or user
A15: String de busca: | B15: ( "total experience" OR multiexperience OR "user experience" OR "customer experience" ) AND ( "online retail" OR e-commerce OR "eletronic commerce" ) AND ( customer OR client OR user ) ( "total experience" OR multiexperience OR "customer experience" ) AND ( "online retail" OR e-commerce OR "eletronic commerce" ) AND ( customer OR client OR user )
A16: Fontes de pesquisa usadas: | B16: ACM, IEEE Xplore, Scopus e Science Direct
A19: Executar as strings nas bases: | B19: Usar ferramentas de busca automáticas, considerando o período de 2015 a 2020, planilhando os resultados.
A20: Primeiros números por fonte de pesquisa: | B20: Hawaii International Conference on System Sciences 2020 (HICSS-53) - 48 resultados ICIS Proceedings - 76 resultados AMCIS Proceedings - 49 resultados Wirtschaftsinformatik Proceedings - 12 resultados International Conference on Information Systems Development (ISD) - 1 resultado
A21: RESULTADO ESPERADO PARTE 2: | B21: String de busca definida e aplicada nas bases de pesquisa. Se os resultados encontrados estão relacionados com o tema, exportar os resultados para uma planilha para que os filtros da Parte 3 possam ser aplicados.
A22: Parte 3: Definindo e Aplicando Filtros
A23: Critérios de exclusão: | B23: CE01- Artigos que não estejam no período de 2015 a 2020; CE02 - Artigos secundários (outra RSL ou MS); CE03 - Artigos com conteúdo pago; CE04 - Artigos duplicados ou similares; CE05 - Artigos indisponíveis para download ou visualização; CE06 - Artigos que não estejam relacionados com as perguntas de pequisa
A24: Critérios de inclusão: | B24: CI01 - Artigos da base AIS CI02 - Artigos que não estejam relacionados com as perguntas de pesquisa
A25: Filtro 1 (Título e Resumo): | B25: Hawaii International Conference on System Sciences 2020 (HICSS-53) - 5 resultados ICIS Proceedings - 8 resultados AMCIS Proceedings - 9 resultados
A26: Filtro 2 (Introdução e Conclusão): | B26: Informar o número de artigos por cada base, após a aplicação do filtro verificando a introdução e conclusão do artigo. Obs: o filtro 2 só é usado caso você não consiga decidir se o artigo é válido ou não usando o filtro 1.
A27: Como os critérios serão aplicados? | B27: Os critérios de exclusão foram aplicados com base no título e resumo (analisando os dados das perguntas de 1 a 5 e utilizando as palavras chaves e conceitos para validar o critério 6) O critério de inclusão 1 foi automatica aprovado em todos, mas com base no critério 6 automaticamente é selecionado ou não.
A28: RESULTADO ESPERADO PARTE 3: | B28: Planilha com a lista de estudos. Os títulos que passaram pelo filtro 1 devem ser pintados de verde, os em dúvida pintados de amarelo e os que não passaram em vermelho. Sinalizar qual o filtro usado para os vermelhos. Os estudos em amarelo deverão passar pelo filtro 2, tornando-se verde ou vermelho.
A29: Parte 4: Qualificando os Estudos
A30: Critérios de qualidade: | B30: Contexto Claro, Metodologia bem definida, Aplicação Prática, Discussão relevantes e consistentes e Limitações e ameaças da pesquisa comentadas
A31: Como os critérios serão aplicados? | B31: Analisar atráves dos critérios de qualidade se o artigo atende ou não as necessidades da nossa qualificação.
A32: RESULTADO ESPERADO PARTE 4: | B32: Planilha com a lista de estudos pintados de verde, acrescentando colunas com os critérios de qualidade. Cada estudo deverá ter uma "nota de qualidade", somando as notas de cada critério. Para valorar o critérios usar a seguinte escala: "0 - não tende; 0.5 - atende parcialmente; 1.0 - atendente totalmente".
A33: Parte 5: Seleção de Artigos
A34: Artigos selecionados por fonte: | B34: Hawaii International Conference on System Sciences 2020 (HICSS-53) - 4 resultados ICIS Proceedings - 7 resultados AMCIS Proceedings - 5 resultados
A35: Artigos selecionados para análise: | B35: Does Being Reputable Drive Customer Equity? Evidence from E-Commerce Web Experience and Growth User Experience in Personalized E-Commerce: A Configurational Approach Biases in Social Commerce Users' Rational Risk Considerations Exploring Trust and Enjoyment in Social Commerce: A Cross-Cultural Research Proposal Contemporary Micro-IT Capabilities and Organizational Performance: The Role of Online Customer Engagement E-Services: An Experience Centric Perspective Deal or No Deal? - Asessing the Daily Deal Shopper Customer Attitude from Social Media, Customer Satisfaction Index, and Firm Value Online Search Behavior in the Air Travel Market: Reconsidering the Consideration Set and Customer Journey Concepts Employing Mixed Reality Applications: Customer Experience Perspective Digital Transformation: Of Paradoxical Tensions and Managerial Responses Towards Developing Trust-Supporting Design Features for AI-Based Chatbots in Customer Service Conversational Agents - Exploring Generative Mechanisms and Second-hand Effects of Actualized Technology Affordances A Mixed Method Approach to Understanding Crowdsourcees’ Engagement Behavior
A36: RESULTADO ESPERADO PARTE 5: | B36: Planilha com a lista de estudos qualificados, com suas respectivas notas de qualidade. Os estudos com notas iguais ou superior a 50% da maior nota e qualidade deverão ser selecionados para a lista final de artigos, ordenada pelo ano de publicação.
A37: Parte 6: Coleta de Evidências
A38: Critérios de responsividade: | B38: 1- Responde, 0.5- Responde parcialmente e 0 - Não
A39: Respostas às questões de pesquisa: | B39: Link para planilha de respostas, informando para cada artigo, qual a questão que ele responde, de acordo com os critérios de responsividade. Não esquecer de guardar evidências das respostas (trecho do artigo).
A40: RESULTADO ESPERADO PARTE 6: | B40: Planilha com a lista finais selecionados, incluindo as colunas com as questões de pesquisa. Para cada questão buscar nos estudo trechos do artigo que respondem a questão.
A41: Parte 7: Análise & Síntese de Dados
A42: Respondendo questões de pesquisa: | B42: Selecionar palavras-chaves (tags) dos trechos selecionados como resposta das questões de pesquisa. Consolidar as respostas a partir destas palavras-chaves. Verificar softwares que possam ajudar nisso.
A43: RESULTADO ESPERADO PARTE 7: | B43: Análise e síntese dos resultados encontrados, de acordo os exemplos recomendados.

Sheet Exemplo 2 - Internet of Behavio
A1: TENDÊNCIAS E DESAFIOS EM SI - ESTRUTURAÇÃO DA INVESTIGAÇÃO SISTEMÁTICA
A2: Parte 1: Planejamento
A3: Integrantes do time:
A4: Tema de pesquisa: | B4: Serviços Baseados em IoT a partir da coleta dos dados pessoais.
A5: Objetivos da pesquisa: | B5: Investigar a influência da coleta dos dados pessoais nos serviços de saúde baseados em IoT. Verificar o impacto dos serviços baseados em IoT na saúde das pessoas.
A6: Motivação/Justificativa: | B6: Este assunto é relevante pois segundo Gartner até 2020 já teríamos a tecnologia de IoT em 95% dos eletrônicos. Soluções desenvolvidas em IoT têm contribuído para avanços na área de saúde. Os dispositivos IoT permitem a coleta de dados em grande volume, online e em tempo real.
A7: Artigos referência (título e link): | B7: http://clyde.dr.ufu.br/bitstream/123456789/24847/3/EstudoAplicacaoSistema.pdf https://revista.fatectq.edu.br/index.php/interfacetecnologica/article/view/515/304 https://lcv.fee.unicamp.br/images/BTSym-17/Papers/72535.pdf https://nvlpubs.nist.gov/nistpubs/ir/2021/NIST.IR.8228pt.pdf https://sci-hub.se/https://ieeexplore.ieee.org/abstract/document/8423891 https://sci-hub.se/https://www.sciencedirect.com/science/article/abs/pii/S0167739X17314127
A8: Questão central de pesquisa: | B8: Como as soluções utilizando IoT estão sendo aplicadas na saúde das pessoas?
A9: Questões secundárias: | B9: Q1 - Quais as tecnologias de IoT estão sendo usadas? Q2 - Que tipo de serviço está sendo utilizado? Q3 - Quais dados estão sendo coletados? Q4 - Qual impacto na saúde das pessoas?
A10: Método: | B10: Revisão.
A11: RESULTADO ESPERADO PARTE 1: | B11: Planejamento da pesquisa, definindo tema, objetivos, motivação, questões de pesquisa, fundamentados por ao menos 2 artigos de referência.
A12: Parte 2: Protocolo de Pesquisa
A13: Palavras-chave: | B13: 1 - Internet of Things 2 - Healthcare 3 - Medicine
A14: Sinônimos por palavras-chave: | B14: Internet of Things - IoT Healthcare - Health- Personal Health Medicine - Preventive Medicine
A15: String de busca: | B15: V1 - (Internet of Things OR IoT) AND (Internet of Behaviors OR IoB) AND (Healthcare OR Preventive Medicine OR Preventive Care OR Personal Health) AND (Big Data Analytics OR Analytics OR Data Analysis) V2 - (Internet of Things OR IoT) AND (Internet of Behaviors OR IoB) AND (Healthcare OR Preventive Medicine OR Preventive Care OR Personal Health) AND (Big Data Analytics OR Data Analysis) V3 - (Internet of Things OR IoT) AND (Internet of Behaviors OR IoB) AND (Healthcare OR Preventive Medicine OR Personal Health) AND (Big Data Analytics OR Data Analysis) V4 - (Internet of Things OR IoT) AND (Internet of Behaviors OR IoB) AND (Healthcare OR Preventive Medicine OR Personal Health) AND (Data Analysis) V5 - (Internet of Things OR IoT) AND (Internet of Behaviors OR IoB) AND (Healthcare OR Preventive Medicine OR Personal Health) AND (Big Data Analytics OR Data Analysis) String Final: ( "Internet of Things" OR IoT ) AND ( "Personal Health" OR Health OR Healthcare ) AND ( Medicine OR "Preventive Medicine" )
A16: Fontes de pesquisa usadas: | B16: ACM, IEEE Xplore, Scopus e Science Direct
A19: Executar as strings nas bases: | B19: https://docs.google.com/spreadsheets/d/10V3_Zgbui7HD5bgSpMVfZfrSk2H8XOczcJvvSw-eSm4/edit#gid=1546267202
A20: Primeiros números por fonte de pesquisa: | B20: AMCIS Proceedings - 24 artigos Hawaii International Conference on System Sciences (HICSS) - 42 artigos ICIS Proceedings - 17 artigos International Conference on Information Systems Development (ISD) - 04 artigos Wirtschaftsinformatik Proceedings - 01 artigo Total de 88 artigos encontrados
A21: RESULTADO ESPERADO PARTE 2: | B21: String de busca definida e aplicada nas bases de pesquisa. Se os resultados encontrados estão relacionados com o tema, exportar os resultados para uma planilha para que os filtros da Parte 3 possam ser aplicados.
A22: Parte 3: Definindo e Aplicando Filtros
A23: Critérios de exclusão: | B23: - Artigos não relacionados ao tema e perguntas da pesquisa - Artigos fora do período da pesquisa (2015 à 2020) - Artigos indisponíveis para visualização - Artigos com conteúdos pagos
A24: Critérios de inclusão: | B24: - Artigos da base AIS - Artigos relacionados ao tema e perguntas da pesquisa - Artigos completos
A25: Filtro 1 (Título e Resumo): | B25: AMCIS Proceedings - 10 artigos Hawaii International Conference on System Sciences (HICSS) - 24 artigos ICIS Proceedings - 06 artigos International Conference on Information Systems Development (ISD) - 02 artigos Total de 42 artigos encontrados
A26: Filtro 2 (Introdução e Conclusão): | B26: AMCIS Proceedings - 03 artigos Hawaii International Conference on System Sciences (HICSS) - 10 artigos ICIS Proceedings - 02 artigos Total de 15 artigos encontrados
A27: Como os critérios serão aplicados? | B27: Durante a pesquisa, utilizamos a ferramenta da base AIS, selecionando assim, apenas artigos da própria base de dados, aplicamos então o filtro de data, excluíndo os artigos fora do período da pesquisa, em seguida tabulamos os resultados e fizemos uma análise individual avaliando os critérios de inclusão e exclusão, primeiramente selecionamos os artigos relacionados ao tema e perguntas da pesquisa, excluindo assim os artigos sem relação com o tema, em seguida utilizamos o título e resumo como como filtro inicial e verificamos as introduções e conclusões dos artigos como segundo filtro, durante o processo de análise podemos avaliar quais artigos possuíam conteúdo pago ou estavam indisponíveis para visualização, os excluíndo assim do processo.
A28: RESULTADO ESPERADO PARTE 3: | B28: Planilha com a lista de estudos. Os títulos que passaram pelo filtro 1 devem ser pintados de verde, os em dúvida pintados de amarelo e os que não passaram em vermelho. Sinalizar qual o filtro usado para os vermelhos. Os estudos em amarelo deverão passar pelo filtro 2, tornando-se verde ou vermelho.
A29: Parte 4: Qualificando os Estudos
A30: Critérios de qualidade: | B30: - Contexto claro - Metodologia bem definida - Proposta bem apresentada - Aplicação prática - Discussões relevantes e consistentes - Limitações e ameaças da pesquisa selecionada.
A31: Como os critérios serão aplicados? | B31: Foram distribuídos os 15 artigos filtrados na Parte 3 entre os membros da equipe, para leitura e análise em concordância com os critérios estabelecidos, sendo atribuídas pontuações de acordo com a escala pré-definida.
A32: RESULTADO ESPERADO PARTE 4: | B32: Planilha com a lista de estudos pintados de verde, acrescentando colunas com os critérios de qualidade. Cada estudo deverá ter uma "nota de qualidade", somando as notas de cada critério. Para valorar o critérios usar a seguinte escala: "0 - não tende; 0.5 - atende parcialmente; 1.0 - atendente totalmente".
A33: Parte 5: Seleção de Artigos
A34: Artigos selecionados por fonte: | B34: AMCIS Proceedings - 02 artigos Hawaii International Conference on System Sciences (HICSS) - 09 artigos ICIS Proceedings - 02 artigos Total de 13 artigos selecionados
A35: Artigos selecionados para análise: | B35: https://docs.google.com/spreadsheets/d/1FeaD2UoM5sB2fkhJYgRnT_PjjyTy7EzvOzXjL8T54Wo/edit#gid=711724059
A36: RESULTADO ESPERADO PARTE 5: | B36: Planilha com a lista de estudos qualificados, com suas respectivas notas de qualidade. Os estudos com notas iguais ou superior a 50% da maior nota e qualidade deverão ser selecionados para a lista final de artigos, ordenada pelo ano de publicação.
A37: Parte 6: Coleta de Evidências
A38: Critérios de responsividade: | B38: Definir critérios para classificação de respostas às perguntas de pesquisa, com escala de valor a sua escolha. Por exemplo, 1- Repsponde, 0.5- Responde parcialmente e 0 - Não responde. Ver exemplos nos artigos do drive da disciplina.
A39: Respostas às questões de pesquisa: | B39: https://docs.google.com/spreadsheets/d/1FeaD2UoM5sB2fkhJYgRnT_PjjyTy7EzvOzXjL8T54Wo/edit#gid=711724059
A40: RESULTADO ESPERADO PARTE 6: | B40: Planilha com a lista finais selecionados, incluindo as colunas com as questões de pesquisa. Para cada questão buscar nos estudo trechos do artigo que respondem a questão.
A41: Parte 7: Análise & Síntese de Dados
A42: Respondendo questões de pesquisa: | B42: Selecionar palavras-chaves (tags) dos trechos selecionados como resposta das questões de pesquisa. Consolidar as respostas a partir destas palavras-chaves. Verificar softwares que possam ajudar nisso.
A43: RESULTADO ESPERADO PARTE 7: | B43: Análise e síntese dos resultados encontrados, de acordo os exemplos recomendados.

Sheet Cópia de Template RSL
A1: Prompt | AA1: //
A2: Parte 2: Protocolo de Pesquisa
A3: Palavras-chave: | B3: AI Agents, Customer Service, Service Automation, Decision Making
A4: Sinônimos por palavras-chave: | B4: Agentes de IA: agentes inteligentes, sistemas autônomos, agentes cognitivos, agentes de software Atendimento ao cliente: Customer Experience, Central de Serviços, Operações de Contact Center Automação de serviços: Automação Inteligente, Otimização de Processos, Automação Robótica de Processos (RPA), Automação de tarefas, Tomada de Decisão: Suporte a decisão
A5: String de busca: | B5: ("AI agents" OR "intelligent agents" OR "cognitive agents" OR "intelligent Agents" OR "autonomous Systems" OR "software Agents") AND ("customer service" OR "customer experience" OR "service center" OR " contact center operations") AND ( "services automation" OR "intelligent automation" OR "smart automation" OR "process optimization" OR "robotic process automation" OR "task automation") AND ("decision making" OR "decision support")
A6: Fontes de pesquisa usadas: | B6: > The influence of artificial intelligence chatbot problem solving on customers’ continued usage intention in e-commerce platforms: an expectation-confirmation model approach > The Art of Talking Machines: A Comprehensive Literature Review of Conversational User Interfaces > From Decision Support to Decision Making: Autonomous AI Agents Shaping the Marketing > AI-driven nudges: Influence of chatbot personas on consumer food choices
A7: Executar a string de busca nas bases: | B7: > ACM > IEEE > Scopus
A8: Primeiros números por fonte de pesquisa: | B8: Para cada base (ou conferência), listar o número de artigos encontrados.
B9: ACM | C9: 178 | D9: https://dl.acm.org/action/doSearch?fillQuickSearch=false&target=advanced&expand=dl&AllField=AllField%3A%28"AI+agents"+OR+"intelligent+agents"+OR+"cognitive+agents"+OR+"autonomous+systems"+OR+"software+agents"%29+AND+AllField%3A%28"customer+service"+OR+"customer+experience"+OR+"contact+center+operations"%29+AND+AllField%3A%28"services+automation"+OR+"intelligent+automation"+OR+"smart+automation"+OR+"process+optimization"+OR+"robotic+process+automation"+OR+"task+automation"%29+AND+AllField%3A%28"decision+making"+OR+"decision+support"%29&AfterYear=2020&BeforeYear=2025&queryID=13%2F9832995874
B10: IEEE | C10: 26 | D10: https://ieeexplore.ieee.org/search/searchresult.jsp?action=search&matchBoolean=true&queryText=(%22All%20Metadata%22:%22AI%20agents%22%20OR%20%22All%20Metadata%22:%22intelligent%20agents%22%20OR%20%22All%20Metadata%22:%22cognitive%20agents%22%20OR%20%22All%20Metadata%22:%22intelligent%20Agents%22%20%20%22autonomous%20Systems%22%20OR.%20%22software%20Agents%22)%20AND%20(%22All%20Metadata%22:%22customer%20service%22%20OR%20%22All%20Metadata%22:%22customer%20experience%22%20OR%20%22All%20Metadata%22:%22central%20de%20servi%C3%A7os%22%20OR%20%22All%20Metadata%22:%22%20contact%20center%20operations%22)%20AND%20(%22All%20Metadata%22:%22Services%20Automation%22%20OR%20%22All%20Metadata%22:%22intelligent%20automation%22%20OR%20%22All%20Metadata%22:%22Smart%20Automation%22%20OR%20%22All%20Metadata%22:%22process%20optimization%22%20OR%20%22All%20Metadata%22:%22robotic%20process%20automation%22%20OR%20%22All%20Metadata%22:%22Task%20Automation%22)%20AND%20(%22All%20Metadata%22:%22Decision%20Making%22%20OR%20%22All%20Metadata%22:%20Decision%20Support%22)&highlight=true&returnType=SEARCH&matchPubs=true&returnFacets=ALL&ranges=2020_2025_Year
B11: Scopus | C11: 226 | D11: https://www.scopus.com/results/results.uri?sort=plf-f&src=s&sid=b60ecc03b8d49e9753ad00f56367fbe4&sot=a&sdt=cl&sl=442&s=%28%22AI+agents%22+OR+%22intelligent+agents%22+OR+%22cognitive+agents%22+OR+%22intelligent+Agents%22+OR+%22autonomous+Systems%22+OR+%22software+Agents%22%29+AND+%28%22customer+service%22+OR+%22customer+experience%22+OR+%22central+de+servi%26%23231%3Bos%22+OR+%22contact+center+operations%22%29+AND+%28%22Services+Automation%22+OR+%22intelligent+automation%22+OR+%22Smart+Automation%22+OR+%22process+optimization%22+OR+%22robotic+process+automation%22+OR+%22Task+Automation%22%29+AND+%28%22Decision+Making%22+OR+%22Decision+Support%22%29&origin=resultslist&editSaveSearch=&txGid=4dfd1e4cdeda15c322ca2696a13e3c1e&sessionSearchId=b60ecc03b8d49e9753ad00f56367fbe4&limit=10&yearFrom=2020&yearTo=2025
B12: Total de Artigos | C12: =SUM(C9:C11) -> 430
A13: Critérios de inclusão: | B13: 1. Investigate the use of AI agents (such as LLMs, multi-agent systems, or reinforcement learning) applied to decision-making or task automation in organizational contexts. 2. Address customer service operations, process automation, or business decision support. 3. Present empirical or experimental evidence, or case studies, on the implementation or impact of these agents. 4. Be available in full text, written in English or Portuguese.
A14: Critérios de exclusão: | B14: 1. Articles that do not directly address AI agents focused on decision-making, organizational automation, or decision support in organizational contexts. 2. Articles without full-text access, either due to lack of open access or unavailability via institutional credentials. 3. Articles published before 2020 . 4. Duplicate records found in different databases or multiple versions of the same study. 5. Short papers or summarized formats, including extended abstracts, posters, short reports, or articles with less than 6 pages of main content.
A15: RESULTADO ESPERADO PARTE 2: | B15: String de busca definida e aplicada nas bases de pesquisa. Se os resultados encontrados estão relacionados com o tema, exportar os resultados para uma planilha para que os filtros da Parte 3 possam ser aplicados.
G56: =450.897777777777 -> 450.89778
G57: /

Sheet Registro de Uso da IA p3
A1: Prompt | C1: System prompt: Assume you are an expert professor in Software Engineering conducting a systematic literature review. Your task is to evaluate studies based on specific criteria: Inclusion Criteria (IC): 1. Investigate the use of AI agents (such as LLMs, multi-agent systems, or reinforcement learning) applied to decision-making or task automation in organizational contexts. 2. Address customer service operations, process automation, or business decision support. 3. Present empirical or experimental evidence, or case studies, on the implementation or impact of these agents. 4. Be available in full text, written in English or Portuguese. Exclusion Criteria (EC): Exclusion criteria from primary candidate study 1. Articles that do not directly address AI agents focused on decision-making, organizational automation, or decision support in organizational contexts. 2. Articles without full-text access, either due to lack of open access or unavailability via institutional credentials. 3. Articles published before 2020 . 4. Duplicate records found in different databases or multiple versions of the same study. 5. Short papers or summarized formats, including extended abstracts, posters, short reports, or articles with less than 6 pages of main content. For scoring, use only 1 or 0: Assign a score of 1 for strong alignment with all inclusion criteria. Assign a score of 0 if any inclusion criteria are not satisfied or if any exclusion criteria are met. You’ll score studies based on their title and abstracts. For the response, use the following format: Response Format: Begin with ‘‘Score: X’’ followed by ‘‘Justification:’’ that explains why the study was considered relevant or not. User prompt: Title: Title of a primary candidate study Abstract: abstract of a primary candidate study
A2: LLM1: CHATGPT | C2: 5.O
A3: LLM2: GEMINI | C3: 2.5 PRO
A4: Base de Dados | B4: Autor(es) | C4: Título do artigo | D4: Ano | E4: URL / DOI | F4: Resumo (abstract) | G4: Palavras-chave principais | H4: Relevância segundo LLM 1 (Sim/Não) | I4: Relevância segundo LLM 2 (Sim/Não) | J4: Diferença entre LLM 1 e LLM 2 | K4: Justificativa da LLM 1 | L4: Justificativa da LLM 2 | M4: LLM que apresentou melhor justificativa (1 ou 2) | N4: Artigo selecionado para a próxima fase
A5: ACM | B5: Mohammad (Matt) Namvarpour, Afsaneh Razi | C5: The Art of Talking Machines: A Comprehensive Literature Review of Conversational User Interfaces | D5: 2025 | E5: https://doi.org/10.1145/3719160.3736621 | F5: This article offers a comprehensive review of Conversational User Interfaces (CUIs), addressing the areas of interface design, systems development, and ethical considerations. The study highlights advancements and challenges in CUIs, such as conversation memory, multimodal interaction, and ethical considerations, as well as suggesting future directions for research. | G5: Conversational User Interfaces, CUI, Revisão de Literatura, Design de Interfaces, Processamento de Linguagem Natural, Ética | H5: Sim | I5: Não | J5: =IF(OR(ISBLANK(H5),ISBLANK(I5)),"",IF(H5<>I5,"Diferente","Igual")) -> Diferente | K5: The study aligns with the inclusion criteria, especially in terms of investigating AI technologies used in task automation and decision support systems. It provides valuable insights into the design, development, and ethical considerations in CUIs, which are related to the task automation in organizational contexts. However, it does not present original empirical evidence, but since it's a comprehensive literature review, it still meets the inclusion criteria. | L5: The article's title and abstract clearly state that it is a "Comprehensive Literature Review" of Conversational User Interfaces (CUIs). A literature review is a form of secondary research that synthesizes the work of others (279 publications in this case ). It does not present new, primary empirical or experimental evidence or a case study of a deployed AI agent, which is a mandatory requirement for inclusion. | M5: LLM 1 | N5: =IF(OR(ISBLANK(H5),ISBLANK(I5)),"", IF(J5="Diferente","Sim",IF(H5="Sim","Sim","Não"))) -> Sim | P5: Mateus
A6: Scopus | B6: Junzhe Gao , Abdullah Promise Opute , Caroline Jawad , Meng Zhan | C6: The influence of artificial intelligence chatbot problem solving on customers’ continued usage intention in e-commerce platforms: an expectation-confirmation model approach | D6: 2025 | E6: https://www.sciencedirect.com/science/article/pii/S0148296325004849?pes=vor&utm_source=scopus&getft_integrator=scopus | F6: The rapid advancement of artificial intelligence (AI) technology has led to its widespread application across various fields, including e-commerce platforms. AI chatbots, powered by large data models, have emerged as a crucial tool for enhancing customer service and user experience. This study aims to investigate the impact of AI chatbot problem-solving capabilities on users’ intention to continue using these services within e-commerce platforms. By integrating elements from the Expectation-Confirmation Model (ECM) and the Technology Acceptance Model (TAM), a comprehensive research model is proposed to examine the relationships between problem-solving, confirmation, perceived ease of use, satisfaction, trust, and continued usage intention. The study employs structural equation modelling (SEM) to analyse data collected from 315 participants through an online questionnaire. The findings reveal that problem-solving abilities positively influence users’ confirmation, which in turn positively affects satisfaction, perceived ease of use, and trust. Furthermore, perceived ease of use exhibits a positive impact on satisfaction, trust, and continued usage intention. Satisfaction and trust have a positive impact on continued usage intention, with satisfaction showing a stronger influence than both problemsolving ability and ease of use. The study contributes to the theoretical understanding of user perceptions and behaviours in AI-driven interactions within e-commerce platforms. It highlights the importance of problemsolving capabilities, perceived ease of use, satisfaction, and trust in driving users’ continued engagement with AI chatbots. Practical implications for AI technology developers and e-commerce companies are discussed, emphasizing the need to focus on enhancing chatbots’ problem-solving proficiency and user-friendliness to foster long-term user retention. Future research directions are proposed, addressing the study’s limitations and exploring the generalizability of the findings beyond the e-commerce context. | G6: AI chatbots E-commerce Problem-solving Expectation-confirmation model Technology acceptance model | H6: Sim | I6: Sim | J6: =IF(OR(ISBLANK(H6),ISBLANK(I6)),"",IF(H6<>I6,"Diferente","Igual")) -> Igual | K6: Score 1 Este artigo investiga a influência das capacidades de resolução de problemas de chatbots de IA no comportamento de uso contínuo dos clientes em plataformas de e-commerce. O estudo foca em como essas capacidades impactam a satisfação, confiança, facilidade de uso percebida e a intenção de continuar usando esses serviços, utilizando um modelo integrado baseado no Modelo de Expectativa-Confirmação (ECM) e no Modelo de Aceitação de Tecnologia (TAM). A pesquisa empírica foi realizada por meio de um modelo de equações estruturais (SEM) com dados de 315 participantes, analisando variáveis como confirmação das expectativas, satisfação, confiança e a facilidade de uso percebida dos chatbots em e-commerce. Pontos principais: Capacidade de resolução de problemas dos chatbots é vista como fundamental para aumentar a intenção de uso contínuo. Satisfação e confiança têm um impacto direto na intenção de continuar o uso do chatbot. A facilidade de uso percebida é um fator significativo que afeta a satisfação e a confiança do usuário, influenciando diretamente sua intenção de continuar utilizando a plataforma. O estudo contribui teoricamente para a compreensão do comportamento do usuário ao interagir com chatbots de IA em plataformas de e-commerce, fornecendo insights sobre o impacto das capacidades de resolução de problemas na satisfação e no engajamento do cliente. Relevância para os critérios de inclusão: Uso de IA aplicada à tomada de decisão e automação de tarefas - O artigo investiga chatbots baseados em IA, focando na resolução de problemas em e-commerce, que é diretamente relacionado à automação de processos de atendimento ao cliente. Atendimento ao cliente e automação de processos - O estudo aborda como os chatbots de IA melhoram o atendimento ao cliente e a experiência do usuário, alinhando-se diretamente a este critério. Evidências empíricas - O estudo utiliza modelagem de equações estruturais (SEM) com dados empíricos, validando o impacto das capacidades dos chatbots no comportamento do consumidor. Disponibilidade em texto completo e em inglês - O artigo está disponível em texto completo e foi escrito em inglês, atendendo ao critério de idioma e acessibilidade. Conclusão: O artigo atende a todos os critérios de inclusão e não apresenta critérios de exclusão que o invalidem. Portanto, ele deve ser selecionado para a próxima fase. | L6: Score: 1 Justification: The study strongly aligns with all inclusion criteria and does not meet any exclusion criteria. IC 1 (AI agents in organizational context): Satisfied. The study investigates "Al chatbots" (an AI agent, specifically noted as "powered by large data models" ) applied within "e-commerce platforms" (an organizational context). IC 2 (Customer service/automation): Satisfied. The abstract explicitly states the focus is on AI chatbots as a "crucial tool for enhancing customer service". IC 3 (Empirical evidence): Satisfied. The abstract details the methodology, stating the "study employs structural equation modelling (SEM) to analyse data collected from 315 participants". IC 4 (Full text/language): Satisfied. The full text is available and written in English. EC 3 (Publication date): Not Met. The article is published in 2025, which is within the required 2020-2025 window. EC 5 (Page length): Not Met. The article is 14 pages long, which is well over the 6-page minimum. | M6: LLM 1 | N6: =IF(OR(ISBLANK(H6),ISBLANK(I6)),"", IF(J6="Diferente","Sim",IF(H6="Sim","Sim","Não"))) -> Sim
A7: IEEE | B7: Sahar Mirzayi, Erfan Talajouran | C7: From Decision Support to Decision Making: Autonomous AI Agents Shaping the Marketing | D7: 2025 | E7: https://ieeexplore.ieee.org/document/11006187 | F7: As artificial intelligence (AI) increasingly drives marketing decisions, understanding its shift from decision support to full autonomy is essential for academia and industry. This paper addresses this gap by analyzing AI's transformative impact on marketing through the lens of the 7Ps framework (Product, Price, Place, Promotion, People, Process, and Physical Evidence). By categorizing AI's role at various levels of autonomy, the study highlights the substantial influence of AI-driven agents, particularly within the Process and Promotion elements where automation has evolved into intelligent decision-making. This research offers a foundational framework for understanding AI autonomy in marketing, providing valuable insights for future marketing strategies. | G7: AI Marketing, Marketing Automation, Autonomous Agents, 7Ps Framework, Decision Making, Decision Support Systems. | H7: Sim | I7: Não | J7: =IF(OR(ISBLANK(H7),ISBLANK(I7)),"",IF(H7<>I7,"Diferente","Igual")) -> Diferente | K7: Score: 1 Justification: Este artigo atende a todos os critérios de inclusão e não viola nenhum critério de exclusão: Investigação do uso de IA aplicada à decisão ou automação em contextos organizacionais O artigo explora a transição da IA de suporte à decisão para tomada de decisão autônoma em marketing, especificamente em e-commerce, o que se alinha diretamente ao critério de aplicação da IA para tomada de decisão e automação de tarefas. Abordar operações de atendimento ao cliente, automação de processos, ou suporte à decisão empresarial O estudo aborda como agentes de IA, como chatbots e sistemas de recomendação, são utilizados para automatizar e otimizar processos de marketing, especialmente nas áreas de promoção e processos, claramente relevantes para o critério. Apresentar evidências empíricas, experimentais ou estudos de caso sobre a implementação ou impacto desses agentes O estudo apresenta uma análise qualitativa baseada em revisão de literatura e exemplos de implementação prática de IA em marketing, discutindo como essas ferramentas impactam estratégias de marketing. Embora não sejam estudos de caso extensivos, o artigo baseia-se em dados práticos e exemplifica o uso real de IA no setor, o que satisfaz parcialmente este critério. Estar disponível em texto completo, escrito em inglês ou português O artigo está disponível em texto completo, em inglês, atendendo a este critério. Além disso, o artigo não se encaixa em nenhuma das categorias de exclusão: Não trata de IA em áreas não relacionadas a decisão ou automação organizacional. Está disponível em texto completo. Não é uma publicação anterior a 2020. Não é um artigo duplicado ou de formato resumido (ex: resumo ou poster). Conclusão: O artigo cumpre os critérios de inclusão e não infringe os critérios de exclusão, sendo aprovado com nota 1. | L7: Score: 0 Justificação: O estudo não atende a todos os critérios de inclusão. Embora o artigo investigue o uso de agentes autônomos de IA (IC 1) aplicados à tomada de decisão e automação de processos no contexto organizacional de marketing (IC 2) , e cumpra os critérios de data (publicado em 2025) e idioma (EC 3, IC 4), ele não satisfaz o Critério de Inclusão 3. O IC 3 exige que o estudo "apresente evidências empíricas ou experimentais, ou estudos de caso". Este artigo é explicitamente uma "revisão narrativa da literatura" e uma proposta de framework teórico. Embora analise "implementações de IA do mundo real" como exemplos para construir seu framework, o estudo em si não é um estudo de caso primário, um experimento ou uma coleta de dados empíricos originais. Sua metodologia é uma revisão qualitativa e exploratória da literatura e de casos públicos. | M7: LLM 1 | N7: =IF(OR(ISBLANK(H7),ISBLANK(I7)),"", IF(J7="Diferente","Sim",IF(H7="Sim","Sim","Não"))) -> Sim
A8: Scopus | B8: Xiyu Guo , Xiaoang Wan | C8: AI-driven nudges: Influence of chatbot personas on consumer food choices | D8: 2025 | E8: https://www.sciencedirect.com/science/article/pii/S019566632500371X?pes=vor&utm_source=scopus&getft_integrator=scopus | F8: Customized chatbot personas can meet the personalized needs of consumers and enhance user engagement in human-chatbot interactions. We conducted a study to investigate the influence of interacting with a chatbot customized as a health coaching assistant versus a gourmet recommendation assistant on participants’ food choices. Participants were instructed to choose three dishes from a set of two meat and two vegetable options to compose a three-dish meal, both before and after they interacted with the health coaching assistant or the gourmet recommendation assistant. The results revealed a significant decrease in the frequency of meat-heavy meal selections after participants interacted with the health coaching assistant, compared to the gourmet recommendation assistant. These findings suggest that interacting with chatbots tailored as health coaching assistants can effectively nudge consumers toward more sustainable food choices. These findings highlight the potential of human-AI interactions in promoting sustainability and offer implications for the design and implementation of chatbots in the restaurant industry. | G8: Food choice Meat reduction Healthy eating Human-AI interaction Chatbot Persona customization | H8: Sim | I8: Sim | J8: =IF(OR(ISBLANK(H8),ISBLANK(I8)),"",IF(H8<>I8,"Diferente","Igual")) -> Igual | K8: Score: 1 Justification: The study “AI-driven nudges: Influence of chatbot personas on consumer food choices” clearly meets all inclusion criteria (IC) and avoids all exclusion criteria (EC): IC1: It investigates AI agents (chatbots based on LLM-like systems) applied to decision-making in an organizational context (restaurant industry). IC2: It addresses customer service operations and business decision support, analyzing how chatbots influence customer choices and potentially enhance service performance in restaurants. IC3: It presents empirical experimental evidence, with controlled tests examining the behavioral impact of chatbot personas on food choices. IC4: The paper is a full-text, peer-reviewed article in English, published in 2025. None of the exclusion criteria (EC) apply: It directly addresses AI agents for decision support and automation. It is fully accessible via institutional and open-access sources. It was published after 2020 (2025). It is not a duplicate, short paper, or abstract-only submission. Hence, the study strongly aligns with the inclusion scope for AI agent applications in decision-making and automation within organizational contexts. | L8: Score: 1 Justification: The study strongly aligns with all inclusion criteria and does not meet any exclusion criteria. IC 1 (AI agents in organizational context): Satisfied. The abstract investigates "chatbots" (AI agents) customized with specific personas to influence "consumer food choices" (decision-making) in the "restaurant industry" (organizational context). IC 2 (Customer service/automation): Satisfied. The study addresses the use of chatbots as a "health coaching assistant" or "gourmet recommendation assistant" , which are forms of customer service and business decision support (by "nudge[ing] consumers"). IC 3 (Empirical evidence): Satisfied. The abstract describes an experimental study where participants made choices "before and after they interacted with the... assistant" , and "The results revealed a significant decrease", presenting clear empirical evidence. IC 4 (Full text/language): Satisfied. The full text is available and is written in English. EC 3 (Publication date): Not Met. The article is published in 2025, which falls within the required 2020-2025 timeframe. EC 5 (Page length): Not Met. The article is 9 pages long, exceeding the 6-page minimum. | M8: LLM 1 | N8: =IF(OR(ISBLANK(H8),ISBLANK(I8)),"", IF(J8="Diferente","Sim",IF(H8="Sim","Sim","Não"))) -> Sim
J9: =IF(OR(ISBLANK(H9),ISBLANK(I9)),"",IF(H9<>I9,"Diferente","Igual")) | N9: =IF(OR(ISBLANK(H9),ISBLANK(I9)),"", IF(J9="Diferente","Sim",IF(H9="Sim","Sim","Não")))
A10: ACM | B10: Modlinski, Artur and Kedziora, Damian and Hak, Andrzej and Motylewski, Jaroslaw and Kedziora, Joanna and Reijers, Hajo A. and del-R\'{\i | C10: Techno-empowerment of&nbsp;Process Automation: Understanding Employee Acceptance of&nbsp;Autonomous AI in&nbsp;Business Processes | D10: 2024 | E10: 10.1007/978-3-031-70396-6_29 | F10: Research in domains such as the car industry and banking has shown people’s acceptance of techno-empowerment, the phenomenon of entrusting technologies with autonomous decision making. An open question is whether process participants are inclined to transfer their decision-making autonomy to software that they are already familiar with yet is extended with AI capabilities. This paper reports on a study carried out to investigate this question by emulating the imminent organizational introduction of techno-empowered, AI-enhanced Robotic Process Automation (RPA). It involved 126 employees within four international companies residing in Poland that had already been routinely applying RPA for the automation of parts of their business processes. Our findings demonstrate the moderating role of (1) workplace perceptions and (2) gender on the effect that perceptions participants on currently used RPA software has on shaping their intentions to techno-empower an AI-enhanced RPA system. A follow-up study with managers within these companies shows that these insights are both new and actionable. As such, our findings help managers to improve their understanding of techno-empowerment dynamics, which is conducive to better predict employees’ reactions to techno-empowered RPA and to plan process change more effectively. | G10: Robotic process automation, hyperautomation, autonomous artificial intelligence, techno-empowerment, digital transformation, technology acceptance | H10: Não | I10: Sim | J10: =IF(OR(ISBLANK(H10),ISBLANK(I10)),"",IF(H10<>I10,"Diferente","Igual")) -> Diferente | K10: Excluded: Does not sufficiently meet inclusion criteria (AI agent or empirical organizational focus not evident). | L10: Justification: This study strongly aligns with all inclusion criteria and does not meet any exclusion criteria. IC 1 (AI Agents in Organizational Contexts): Investigates AI-enhanced Robotic Process Automation (RPA), which are autonomous AI systems used for task automation and decision-making in an organizational context (business processes). IC 2 (Organizational Application): Directly addresses process automation in business processes within international companies. IC 3 (Empirical Evidence): Presents empirical evidence via a study involving 126 employees and a follow-up study with managers, investigating employee intentions toward "techno-empowered" AI systems. IC 4 (Full Text/Language): The title and abstract are in English, and it's a full-length article published in a conference proceeding (implied full text). EC 3 (Publication Date): Published in 2024 (after 2020). | M10: LLM 2 | N10: =IF(OR(ISBLANK(H10),ISBLANK(I10)),"", IF(J10="Diferente","Sim",IF(H10="Sim","Sim","Não"))) -> Sim
A11: ACM | B11: Huang, Tian and Yu, Chun and Shi, Weinan and Peng, Zijian and Yang, David and Sun, Weiqi and Shi, Yuanchun | C11: Prompt2Task: Automating UI Tasks on Smartphones from Textual Prompts | D11: 2025 | E11: 10.1145/3716132 | F11: UI task automation enables efficient task execution by simulating human interactions with GUIs, without modifying the existing application code. However, its broader adoption is constrained by the need for expertise in both scripting languages and workflow design. To address this challenge, we present Prompt2Task, a system designed to comprehend various task-related textual prompts (e.g., goals, procedures), thereby generating and performing the corresponding automation tasks. Prompt2Task incorporates a suite of intelligent agents that mimic human cognitive functions, specializing in interpreting user intent, managing external information for task generation, and executing operations on smartphones. The agents can learn from user feedback and continuously improve their performance based on the accumulated knowledge. Experimental results indicated a performance jump from a 22.28% success rate in the baseline to 95.24% with Prompt2Task, requiring an average of 0.69 user interventions for each new task. Prompt2Task presents promising applications in fields such as tutorial creation, smart assistance, and customer service. | G11: UI task automation, UI navigation, natural language, UI understanding, large language models | H11: Não | I11: Sim | J11: =IF(OR(ISBLANK(H11),ISBLANK(I11)),"",IF(H11<>I11,"Diferente","Igual")) -> Diferente | K11: Excluded: Does not sufficiently meet inclusion criteria (AI agent or empirical organizational focus not evident). | L11: Justification: This study strongly aligns with all inclusion criteria and does not meet any exclusion criteria. IC 1 (AI Agents in Organizational Contexts): Describes a system (Prompt2Task) that incorporates a suite of intelligent agents (mimicking human cognitive functions) for task automation driven by Large Language Models (LLMs). IC 2 (Organizational Application): Mentions promising applications in fields such as customer service. IC 3 (Empirical Evidence): Presents experimental results indicating a performance jump and success rate improvement (e.g., from 22.28% to 95.24%), providing quantitative empirical evidence. IC 4 (Full Text/Language): The title and abstract are in English, and it's a full-length article published in a conference proceeding (implied full text). EC 3 (Publication Date): Published in 2025 (after 2020). | M11: LLM 2 | N11: =IF(OR(ISBLANK(H11),ISBLANK(I11)),"", IF(J11="Diferente","Sim",IF(H11="Sim","Sim","Não"))) -> Sim
A12: ACM | B12: Sun, Yu-Zhu and Sun, He-Li and Ma, Jian-Cong and Zhang, Peng and Huang, Xiao-Yong | C12: Multimodal Agent AI: A Survey of Recent Advances and Future Directions | D12: 2025 | E12: 10.1007/s11390-025-4802-8 | F12: In recent years, multimodal agent AI (MAA) has emerged as a pivotal area of research, holding promise for transforming human-machine interaction. Agent AI systems, capable of perceiving and responding to inputs from multiple modalities (e.g., language, vision, audio), have demonstrated remarkable progress in understanding complex environments and executing intricate tasks. This survey comprehensively reviews the state-of-the-art developments in MAA and examines its fundamental concepts, key techniques, and applications across diverse domains. We first introduce the basics of agent AI and its multimodal interaction capabilities. We then delve into the core technologies that enable agents to perform task planning, decision-making, and multi-sensory fusion. Furthermore, we focus on exploring various applications of MAA in robotics, healthcare, gaming, and beyond. Additionally, we mainly focus on analyzing the challenges and limitations of current systems and propose promising research directions for future improvements, including human-AI collaboration, online learning method improvement. By reviewing existing work and highlighting open questions, this survey aims to provide a comprehensive roadmap for researchers and practitioners in the field of MAA. | G12: multimodal agent AI, task planning, decision making, robotic, healthcare | H12: Não | I12: Não | J12: =IF(OR(ISBLANK(H12),ISBLANK(I12)),"",IF(H12<>I12,"Diferente","Igual")) -> Igual | K12: Excluded: Does not sufficiently meet inclusion criteria (AI agent or empirical organizational focus not evident). | L12: Justification: This study is excluded because it fails to satisfy Inclusion Criterion 3 and meets Exclusion Criterion 5. IC 3 (Empirical Evidence): This is a survey ("comprehensively reviews the state-of-the-art developments"), which synthesizes existing research but does not present new empirical or experimental evidence, or case studies of its own on the implementation or impact of the agents. EC 5 (Short Papers/Summarized Formats): Surveys, literature reviews, and roadmaps often fail to meet the "less than 6 pages of main content" criteria or the requirement for presenting primary empirical data (though this is primarily based on the failure of IC 3). The primary reason for exclusion is failure to provide new empirical evidence (IC 3). | M12: LLM 2 | N12: =IF(OR(ISBLANK(H12),ISBLANK(I12)),"", IF(J12="Diferente","Sim",IF(H12="Sim","Sim","Não"))) -> Não
A13: ACM | B13: Zhang, Liang-Jie and Chen, Huan and He, Sheng and Li, Changhu and Chen, Junyang and Zhang, Haodi and Du, Wenfeng | C13: COSIS: An AI-Enabled Digital Transformation Framework Integrating Large Language Models and Key Performance Indicators | D13: 2024 | E13: 10.1007/978-3-031-77000-5_6 | F13: The rapid advancement of Artificial Intelligence (AI) and Large Language Models (LLMs) has significantly transformed various sectors of society, compelling enterprises to undertake comprehensive digital transformations to remain competitive in the AI era. This paper introduces COSIS, an AI-enabled digital trans-formation framework comprising five key dimensions: Culture, Operation, Strategy, Innovation, and Service. The COSIS framework provides a structured approach for enterprises to navigate the complexities of digital transformation by integrating AI and LLM technologies into their core functions. For each dimension, the paper identifies specific key performance indicators (KPIs) to measure the effectiveness of AI-enabled transformations. These KPIs enable enterprises to quantitatively assess progress and outcomes, ensuring alignment with strategic objectives and facilitating continuous improvement. Additionally, the paper discusses the implications of AI and LLM technologies on enterprise management team building in the AI era. | G13: Artificial Intelligence, Large Language Models, Digital Transformation, COSIS Framework, Key Performance Indicators, Enterprise Management, Culture, Operation, Strategy, Innovation, Service | H13: Não | I13: Não | J13: =IF(OR(ISBLANK(H13),ISBLANK(I13)),"",IF(H13<>I13,"Diferente","Igual")) -> Igual | K13: Excluded: Does not sufficiently meet inclusion criteria (AI agent or empirical organizational focus not evident). | L13: Justification: This study is excluded because it fails to satisfy Inclusion Criterion 3. IC 1 & 2 (AI Agents/Organizational Context): The study addresses AI and LLM technologies for digital transformation across various enterprise dimensions (Culture, Operation, Strategy, Innovation, Service), which is relevant. IC 3 (Empirical Evidence): The abstract introduces a framework (COSIS) and discusses its implications, but it does not mention presenting any empirical or experimental evidence, or case studies on the implementation or impact of the LLMs/AI agents themselves. It is a conceptual/framework paper. | M13: LLM 2 | N13: =IF(OR(ISBLANK(H13),ISBLANK(I13)),"", IF(J13="Diferente","Sim",IF(H13="Sim","Sim","Não"))) -> Não
A14: ACM | B14: Pereira, Leandro and Tom\'{a | C14: How artificial intelligence can improve digital marketing | D14: 2023 | E14: 10.1504/ijbis.2023.135351 | F14: Recent technological advances have allowed the growth of digital marketing, creating the challenge of big data. AI emerges to deal with this paradigm and marketing becomes a natural beneficiary, as it takes advantage of data in its processes. This research aims to evaluate the potential impact of AI on digital marketing. This knowledge could accelerate the adoption of AI technologies, revolutionising the area. The following techniques were developed: survey for digital marketing professionals to identify their needs; research of AI solutions; coverage and match analysis between needs and solutions. This research establishes which digital marketing aspects need further development and recommends response solutions: Bloomreach Experience Cloud for customer experience; Alli AI and Market Brew for SEO; concured for content marketing; Automizy for e-mail marketing; Cortex for social media marketing; Adobe Advertising Cloud for online advertising; Conversica and drift automation for communication; and SAS VDMML and SAS VF for data analysis. | G14: artificial intelligence, marketing, digital marketing | H14: Não | I14: Não | J14: =IF(OR(ISBLANK(H14),ISBLANK(I14)),"",IF(H14<>I14,"Diferente","Igual")) -> Igual | K14: Excluded: Does not sufficiently meet inclusion criteria (AI agent or empirical organizational focus not evident). | L14: Justification: This study is excluded because it fails to satisfy Inclusion Criterion 3. IC 1 & 2 (AI Agents/Organizational Context): The study investigates the impact of AI on digital marketing, which involves organizational decision-making/process automation. It researches AI solutions (e.g., Automizy, Drift automation). IC 3 (Empirical Evidence): The methodology involves a survey of professionals and research of AI solutions, followed by coverage/match analysis. While a survey is empirical, the core of the study is an evaluation of potential impact and a recommendation of solutions (not an implementation or impact study of a specific agent/system). It does not present empirical data on the actual implementation or impact of a specific AI agent within an organizational setting that meets the criteria. | M14: LLM 2 | N14: =IF(OR(ISBLANK(H14),ISBLANK(I14)),"", IF(J14="Diferente","Sim",IF(H14="Sim","Sim","Não"))) -> Não
A15: ACM | B15: Dang, Jiawei and Chen, Huan and He, Sheng and Huang, Hongbo and Zhang, Liang-Jie | C15: IMPRESSIVE: An AI Enterprise Model and&nbsp;Maturity Assessment Framework for&nbsp;Intelligent Transformation | D15: 2025 | E15: 10.1007/978-3-032-06310-6_4 | F15: As AI becomes a core driver of enterprise transformation, traditional organizations face challenges such as rigid structures, data fragmentation, and outdated evaluation models. Existing digital transformation maturity models focus primarily on IT infrastructure and industrial-era processes, lacking a comprehensive framework&nbsp;for evaluating AI effectiveness. To address this gap, this&nbsp;paper proposes the IMPRESSIVE Enterprise Framework, which defines&nbsp;ten critical capabilities for AI-powered organizations: Innovation, Machine Learning, Personalization, Reliability, Enhanced Experience, Scalability, Security, Integrated Ecosystem, Value-Driven Culture, and Efficiency. Derived from this framework, the IMPRESSIVE Maturity Assessment Model (IMAM) is developed as a quantitative tool&nbsp;to measure AI maturity across these dimensions. Validation through&nbsp;case studies demonstrates IMAM’s applicability in identifying strengths, gaps, and strategic pathways for enterprises transitioning&nbsp;to AI-native operations. This research contributes a holistic framework to guide organizations in systematically navigating&nbsp;AI transformation, bridging the gap between theoretical insights&nbsp;and actionable practice. | G15: AI-driven Transformation, Enterprise Maturity Assessment, Maturity Model, Model Context Protocol(MCP) | H15: Não | I15: Não | J15: =IF(OR(ISBLANK(H15),ISBLANK(I15)),"",IF(H15<>I15,"Diferente","Igual")) -> Igual | K15: Excluded: Does not sufficiently meet inclusion criteria (AI agent or empirical organizational focus not evident). | L15: Justification: This study is excluded because it fails to satisfy Inclusion Criterion 3. IC 1 & 2 (AI Agents/Organizational Context): The study addresses an AI Enterprise Framework and a Maturity Assessment Model (IMAM) for AI-driven transformation in organizations, which is relevant. IC 3 (Empirical Evidence): The abstract introduces the framework and model, and while it mentions "Validation through case studies demonstrates IMAM’s applicability," the primary focus is on the framework/model itself, not on the empirical implementation or impact of an AI agent used for decision-making or task automation in an organizational context. It is a framework/maturity assessment paper. | M15: LLM 2 | N15: =IF(OR(ISBLANK(H15),ISBLANK(I15)),"", IF(J15="Diferente","Sim",IF(H15="Sim","Sim","Não"))) -> Não
A16: ACM | B16: Drouin, Alexandre and Gasse, Maxime and Caccia, Massimo and Laradji, Issam H. and Verme, Manuel Del and Marty, Tom and Vazquez, David and Chapados, Nicolas and Lacoste, Alexandre | C16: WorkArena: how capable are web agents at solving common knowledge work tasks? | D16: 2024 | E16: https://arxiv.org/abs/2403.07718 | F16: We study the use of large language model-based agents for interacting with software via web browsers. Unlike prior work, we focus on measuring the agents' ability to perform tasks that span the typical daily work of knowledge workers utilizing enterprise software systems. To this end, we propose WorkArena, a remote-hosted benchmark of 33 tasks based on the widely-used ServiceNow platform. We also introduce BrowserGym, an environment for the design and evaluation of such agents, offering a rich set of actions as well as multimodal observations. Our empirical evaluation reveals that while current agents show promise onWorkArena, there remains a considerable gap towards achieving full task automation. Notably, our analysis uncovers a significant performance disparity between open and closed-source LLMs, highlighting a critical area for future exploration and development in the field. | H16: Sim | I16: Sim | J16: =IF(OR(ISBLANK(H16),ISBLANK(I16)),"",IF(H16<>I16,"Diferente","Igual")) -> Igual | K16: Included: Addresses AI agents applied to decision-making or automation in organizational contexts with empirical evidence. | L16: Justification: This study strongly aligns with all inclusion criteria and does not meet any exclusion criteria. IC 1 (AI Agents in Organizational Contexts): Focuses on large language model-based agents (LLM agents) used for interacting with software via web browsers to perform knowledge work tasks. IC 2 (Organizational Application): The tasks are based on the widely-used ServiceNow platform, which is a system for business decision support and task automation in an organizational context. IC 3 (Empirical Evidence): Presents empirical evaluation on the agents' ability to perform tasks, providing data on performance disparity, which constitutes experimental evidence. IC 4 (Full Text/Language): The title and abstract are in English, and it is available as a full-text preprint (arXiv), which is acceptable for a review at this stage. EC 3 (Publication Date): Published in 2024 (after 2020). | M16: LLM 2 | N16: =IF(OR(ISBLANK(H16),ISBLANK(I16)),"", IF(J16="Diferente","Sim",IF(H16="Sim","Sim","Não"))) -> Sim
A17: ACM | B17: He, Jessica and Piorkowski, David and Muller, Michael and Brimijoin, Kristina and Houde, Stephanie and Weisz, Justin | C17: Rebalancing Worker Initiative and AI Initiative in Future Work: Four Task Dimensions | D17: 2023 | E17: 10.1145/3596671.3598572 | F17: Organizations have recently begun to deploy conversational task assistants that collaborate with knowledge workers to partially automate their work tasks. These assistants evolved out of business robotic process automation (RPA) tools and are becoming more intelligent: users can initiate task sequences through natural language, and the system can orchestrate those tasks if they have not previously been defined. As these tools become more automated, system designers tend to optimize overall process efficiency, but at the cost of shifting agency away from workers. Particularly in high stakes work environments, this shift raises questions of how to re-delegate agency such that workers feel sufficiently in control of automated tasks. We explored this through two studies comprised of interviews and co-design activities with knowledge workers and identified four task dimensions along which their automation and interaction preferences vary: process consequence, social consequence, task familiarity, and task complexity. These dimensions are useful for understanding when, why, and how to delegate agency between workers and conversational task assistants. | G17: Agent skills, Intelligent agent, Orchestration of work, Participatory design., Task assistant | H17: Não | I17: Sim | J17: =IF(OR(ISBLANK(H17),ISBLANK(I17)),"",IF(H17<>I17,"Diferente","Igual")) -> Diferente | K17: Excluded: Does not sufficiently meet inclusion criteria (AI agent or empirical organizational focus not evident). | L17: Justification: This study strongly aligns with all inclusion criteria and does not meet any exclusion criteria. IC 1 (AI Agents in Organizational Contexts): Investigates conversational task assistants (AI agents) that collaborate with knowledge workers to partially automate their work tasks. IC 2 (Organizational Application): Directly relates to the evolution of business robotic process automation (RPA) tools and the orchestration of tasks in organizational settings. IC 3 (Empirical Evidence): Presents empirical evidence from "two studies comprised of interviews and co-design activities with knowledge workers," identifying task dimensions based on worker preferences. IC 4 (Full Text/Language): The title and abstract are in English, and it is a full-length article published in a conference proceeding (implied full text). EC 3 (Publication Date): Published in 2023 (after 2020). | M17: LLM 2 | N17: =IF(OR(ISBLANK(H17),ISBLANK(I17)),"", IF(J17="Diferente","Sim",IF(H17="Sim","Sim","Não"))) -> Sim
A18: ACM | B18: Pereira, Leandro and R\'{e | C18: Artificial intelligence in strategic business management: the case of auditing | D18: 2024 | E18: 10.1504/ijbis.2024.135970 | F18: We live in the era of digital transformation and adopting innovative tools and technologies such as artificial intelligence (AI) seems to be extolling business models and driving optimisation in the processes inherent to their operation. In the audit area, which is intense in tasks that can be performed by machines, studies emerge showing positive results in the adoption of AI tools. The literature affirms the use of machinery such as AI in business models opens doors to the creation of value in organisations adjacent to this strategy. In order to deepen this contradictory approach between the benefits associated with the adoption of AI and the low rate of use of it, around 200 employees from mostly Portuguese companies were inquired. The research findings allow the understanding of what kind of work can be transferred for AI automatisation and present a list of technological issues to solve in this transformation. | G18: auditing, innovation, innovation processes, technology adoption, technological change, technological innovation | H18: Não | I18: Sim | J18: =IF(OR(ISBLANK(H18),ISBLANK(I18)),"",IF(H18<>I18,"Diferente","Igual")) -> Diferente | K18: Excluded: Does not sufficiently meet inclusion criteria (AI agent or empirical organizational focus not evident). | L18: Justification: This study strongly aligns with all inclusion criteria and does not meet any exclusion criteria, provided the full-text confirms it's not a short paper. IC 1 (AI Agents in Organizational Contexts): Addresses the adoption of AI tools in the audit area, which involves task automation and strategic business management. IC 2 (Organizational Application): Focuses on the auditing area, a critical business decision support/process automation context. IC 3 (Empirical Evidence): States that "around 200 employees from mostly Portuguese companies were inquired," and the findings allow understanding what kind of work can be transferred for AI automatisation, which provides empirical evidence via a survey. IC 4 (Full Text/Language): The title and abstract are in English/Portuguese, and it is a full-length article published in a journal (implied full text). EC 3 (Publication Date): Published in 2024 (after 2020). | M18: LLM 2 | N18: =IF(OR(ISBLANK(H18),ISBLANK(I18)),"", IF(J18="Diferente","Sim",IF(H18="Sim","Sim","Não"))) -> Sim
A19: ACM | B19: Varriale, Vincenzo and Cammarano, Antonello and Michelino, Francesca and Caputo, Mauro | C19: Critical analysis of the impact of artificial intelligence integration with cutting-edge technologies for production systems | D19: 2023 | E19: 10.1007/s10845-023-02244-8 | F19: Scientific research on emerging technologies underscored the advantages of their implementation within production systems, with a particular focus on artificial intelligence (AI). In particular, the integration of AI with other cutting-edge technologies is a relevant topic which can potentially lead to huge impacts in terms of business performance. Yet, literature on the subject, although rich, is still fragmented, limited to specific cases and applications, but lacking in a comprehensive classification framework. Therefore, using a systematic literature review, this study provides an overview of how the combination of AI and other cutting-edge technologies could potentially improve market and organisational performance in business functions and processes. By classifying the literature of case studies and real-world applications into specific taxonomies, the research considers an indicator, the co-occurrence ratio, highlighting the most significant and emerging combinations between AI and other cutting-edge technologies, also specifying the contexts in which they are used. The study shows that AI is strongly interconnected with other cutting-edge technologies, suggesting a research agenda in which the integration of AI with other emerging technologies is promising within specific production systems contexts, providing benefits and opportunities for companies. | G19: Artificial intelligence, Emerging technologies, Production systems, Operations management | H19: Não | I19: Não | J19: =IF(OR(ISBLANK(H19),ISBLANK(I19)),"",IF(H19<>I19,"Diferente","Igual")) -> Igual | K19: Excluded: Does not sufficiently meet inclusion criteria (AI agent or empirical organizational focus not evident). | L19: Justification: This study is excluded because it fails to satisfy Inclusion Criterion 3 and meets Exclusion Criterion 5. IC 3 (Empirical Evidence): This is a systematic literature review ("using a systematic literature review, this study provides an overview..."), which classifies existing case studies and real-world applications but does not present new empirical or experimental evidence of its own on the implementation or impact of the agents. EC 5 (Short Papers/Summarized Formats): Literature reviews are generally considered secondary studies and are excluded primarily because they do not contain the primary empirical data required by IC 3. The primary reason for exclusion is failure to provide new empirical evidence (IC 3). | M19: LLM 2 | N19: =IF(OR(ISBLANK(H19),ISBLANK(I19)),"", IF(J19="Diferente","Sim",IF(H19="Sim","Sim","Não"))) -> Não
A20: ACM | B20: Enholm, Ida Merete and Papagiannidis, Emmanouil and Mikalef, Patrick and Krogstie, John | C20: Artificial Intelligence and Business Value: a Literature Review | D20: 2022 | E20: 10.1007/s10796-021-10186-w | F20: Artificial Intelligence (AI) are a wide-ranging set of technologies that promise several advantages for organizations in terms off added business value. Over the past few years, organizations are increasingly turning to AI in order to gain business value following a deluge of data and a strong increase in computational capacity. Nevertheless, organizations are still struggling to adopt and leverage AI in their operations. The lack of a coherent understanding of how AI technologies create business value, and what type of business value is expected, therefore necessitates a holistic understanding. This study provides a systematic literature review that attempts to explain how organizations can leverage AI technologies in their operations and elucidate the value-generating mechanisms. Our analysis synthesizes the current literature and highlights: (1) the key enablers and inhibitors of AI adoption and use; (2) the typologies of AI use in the organizational setting; and (3) the first- and second-order effects of AI. The paper concludes with an identification of the gaps in the literature and develops a research agenda that identifies areas that need to be addressed by future studies. | G20: Artificial intelligence, Systematic literature review, Research agenda, Artificial intelligence capabilities | H20: Não | I20: Não | J20: =IF(OR(ISBLANK(H20),ISBLANK(I20)),"",IF(H20<>I20,"Diferente","Igual")) -> Igual | K20: Excluded: Does not sufficiently meet inclusion criteria (AI agent or empirical organizational focus not evident). | L20: Justification: This study is excluded because it fails to satisfy Inclusion Criterion 3 and meets Exclusion Criterion 5. IC 3 (Empirical Evidence): This is a systematic literature review ("This study provides a systematic literature review..."), which synthesizes existing literature but does not present new empirical or experimental evidence, or case studies of its own on the implementation or impact of the agents. EC 5 (Short Papers/Summarized Formats): Literature reviews are generally considered secondary studies and are excluded primarily because they do not contain the primary empirical data required by IC 3. The primary reason for exclusion is failure to provide new empirical evidence (IC 3). | M20: LLM 2 | N20: =IF(OR(ISBLANK(H20),ISBLANK(I20)),"", IF(J20="Diferente","Sim",IF(H20="Sim","Sim","Não"))) -> Não
A21: ACM | B21: Wamba, Samuel Fosso and Wamba-Taguimdje, Serge-Lopez and Twinomurinzi, Hossana | C21: Why Should Users Take the Risk of Sustainable Use of Generative Artificial Intelligence Chatbots: An Exploration of ChatGPT's Use | D21: 2024 | E21: 10.4018/JGIM.365600 | F21: Despite the risks associated with generative AI (GenAI) chatbots, people increasingly use these technologies, which may seem contradictory. This study identified and explored factors and risks related to trust, perceived values, satisfaction, and sustainable use of GenAI chatbots. Relying on IS theories to build a stimulus-organism-response model, the authors tested a model using PLS-SEM with data from 393 ChatGPT users. The results show that user competence and autonomy dramatically increase a user's trust in ChatGPT, and trust improves hedonic value (HV), utilitarian value (UV), value-in-use, perceived task-technology fit (TTF), information accuracy, knowledge acquisition, perceived informativeness, and user satisfaction. In addition to trust, user satisfaction depends on HV, UV, and TTF. The sustainability use of ChatGPT depends on HV and satisfaction. However, perceived privacy concerns, perceived privacy risks, and privacy awareness do not affect consumer trust. There is a complete mediation between trust and sustainability, as well as HV and sustainability. | G21: ChatGPT, GenAI-Chatbot, Artificial Intelligence, Risks, User Satisfaction, Sustainable Use | H21: Não | I21: Sim | J21: =IF(OR(ISBLANK(H21),ISBLANK(I21)),"",IF(H21<>I21,"Diferente","Igual")) -> Diferente | K21: Excluded: Does not sufficiently meet inclusion criteria (AI agent or empirical organizational focus not evident). | L21: Justification: This study strongly aligns with all inclusion criteria and does not meet any exclusion criteria. IC 1 (AI Agents in Organizational Contexts): Explores factors related to the use of Generative AI (GenAI) chatbots (like ChatGPT), which function as AI agents for decision support/task assistance. IC 2 (Organizational Application): Relates to the sustainable use of these tools by people, which is directly applicable to organizational adoption and integration. IC 3 (Empirical Evidence): Tested a model using PLS-SEM with data from 393 ChatGPT users, which constitutes empirical evidence. IC 4 (Full Text/Language): The title and abstract are in English, and it is a full-length article published in a journal (implied full text). EC 3 (Publication Date): Published in 2024 (after 2020). | M21: LLM 2 | N21: =IF(OR(ISBLANK(H21),ISBLANK(I21)),"", IF(J21="Diferente","Sim",IF(H21="Sim","Sim","Não"))) -> Sim
A22: ACM | B22: French, Aaron M. and Shim, J. P. | C22: From Artificial Intelligence to Augmented Intelligence: A Shift in Perspective, Application, and Conceptualization of AI | D22: 2024 | E22: 10.1007/s10796-024-10562-2 | F22: This paper provides a comprehensive examination of the ongoing debate surrounding Artificial Intelligence (AI) and its societal implications, with a particular focus on job displacement. The release of generative AI tools for public use, particularly ChatGPT, has created numerous concerns on how these tools will be used and adverse impacts on society. Augmented Intelligence has been introduced as a concept utilizing AI to enhance human capabilities but its distinction as an assistive role is ill-defined. This research provides insights into the reconceptualization of AI as Augmented Intelligence examining their differences in terms of knowledge development, decision-making, and outcomes. Through three case studies, we demonstrate the assistive role of Augmented Intelligence and how it can serve as a catalyst for job creation and cognitive enhancement. We also explore the impact of AI and IA tools as a sociotechnical system and their effect on human cognitive abilities through the theoretical lens of the Dunning Kruger Effect. We conclude with a research agenda to stimulate future directions of research. | G22: Intelligence augmentation (IA), Artificial intelligence (AI), Generative AI, Dunning kruger effect, Machine learning, ChatGPT | H22: Não | I22: Sim | J22: =IF(OR(ISBLANK(H22),ISBLANK(I22)),"",IF(H22<>I22,"Diferente","Igual")) -> Diferente | K22: Excluded: Does not sufficiently meet inclusion criteria (AI agent or empirical organizational focus not evident). | L22: Justification: This study strongly aligns with all inclusion criteria and does not meet any exclusion criteria. IC 1 (AI Agents in Organizational Contexts): Examines Generative AI and Augmented Intelligence (IA), which utilizes AI to enhance human capabilities in decision-making and cognitive enhancement. IC 2 (Organizational Application): Focuses on the societal/organizational implications of these tools, including job creation and use in a sociotechnical system. IC 3 (Empirical Evidence): States, "Through three case studies, we demonstrate the assistive role of Augmented Intelligence," which provides case study evidence. IC 4 (Full Text/Language): The title and abstract are in English, and it is a full-length article published in a journal (implied full text). EC 3 (Publication Date): Published in 2024 (after 2020). | M22: LLM 2 | N22: =IF(OR(ISBLANK(H22),ISBLANK(I22)),"", IF(J22="Diferente","Sim",IF(H22="Sim","Sim","Não"))) -> Sim
A23: ACM | C23: AAMAS '25: Proceedings of the 24th International Conference on Autonomous Agents and Multiagent Systems | D23: 2025 | E23: https://dl.acm.org/doi/proceedings/10.5555/3709347 | F23: Welcome to AAMAS-2025, the 24th edition of the International Conference on Autonomous Agents and Multiagent Systems!AAMAS is the largest and most influential conference in the area of agents and multiagent systems, bringing together researchers and practitioners in all areas of agent technology and providing an internationally renowned high-profile forum for publishing and learning about the latest developments in the field. AAMAS is the flagship conference of the non-profit International Foundation for Autonomous Agents and Multiagent Systems (IFAAMAS).We are happy that the 2025 edition of AAMAS will be coming to Detroit, MI. Previous editions were held in Bologna (2002), Melbourne (2003), New York (2004), Utrecht (2005), Hakodate (2006), Honolulu (2007), Estoril (2008), Budapest (2009), Toronto (2010), Taipei (2011), Valencia (2012), Saint Paul (2013), Paris (2014), Istanbul (2015), Singapore (2016), S\~{a | H23: Não | I23: Não | J23: =IF(OR(ISBLANK(H23),ISBLANK(I23)),"",IF(H23<>I23,"Diferente","Igual")) -> Igual | K23: Excluded: Does not sufficiently meet inclusion criteria (AI agent or empirical organizational focus not evident). | L23: Justification: This item is excluded because it is an announcement/introduction to a conference proceedings, not a primary research study. EC 5 (Short Papers/Summarized Formats): This is a conference introduction/proceedings note, not a full-length research article with primary content. | M23: LLM 2 | N23: =IF(OR(ISBLANK(H23),ISBLANK(I23)),"", IF(J23="Diferente","Sim",IF(H23="Sim","Sim","Não"))) -> Não
A24: ACM | B24: Wang, Yahui and Guizani, Mohsen and Hossain, M. Shamim | C24: Artificial Intelligence for Virtual Reality: State of the Art, Challenges, and Future Perspectives | D24: 2025 | E24: 10.1145/3769090 | F24: Artificial Intelligence (AI) has wide applications in virtual reality (VR), especially in analyzing its implementation progress, existing limitations, and future development paths. This study finds that AI's main contributions to VR are in four key areas: creating intelligent virtual characters, advancing education and training, providing medical assistance, and generating dynamic scenes. This interdisciplinary convergence also brings significant opportunities, particularly in sectors such as education, healthcare, gaming, and corporate training. Additionally, the study discusses technical challenges related to computational costs, real-time feedback, user privacy, and algorithmic ethics. Critical challenges persist in data processing bottlenecks, privacy protection issues, and user adaptation. While AI enhances VR's intelligence and interactivity, breakthroughs are still needed in cross-modal integration, privacy, security, and user experience. Future advancements in deep learning and reinforcement learning may unlock unlimited potential for AI-driven VR in personalized adaptation and immersive interaction. Therefore, this study provides a comprehensive analysis of AI–VR integration, providing valuable insights for academic research and technological development. | G24: Artificial Intelligence, Virtual Reality, Intelligent Interaction, Digital Twins, User Experience, Privacy Security | H24: Sim | I24: Não | J24: =IF(OR(ISBLANK(H24),ISBLANK(I24)),"",IF(H24<>I24,"Diferente","Igual")) -> Diferente | K24: Included: Addresses AI agents applied to decision-making or automation in organizational contexts with empirical evidence. | L24: Justification: This study is excluded because it fails to satisfy Inclusion Criterion 3 and meets Exclusion Criterion 5. IC 3 (Empirical Evidence): This is a survey ("This study provides a comprehensive analysis..."), which reviews the integration of AI and VR but does not present new empirical or experimental evidence, or case studies of its own on the implementation or impact of the agents. EC 5 (Short Papers/Summarized Formats): Surveys are generally considered secondary studies and are excluded primarily because they do not contain the primary empirical data required by IC 3. The primary reason for exclusion is failure to provide new empirical evidence (IC 3). | M24: LLM 2 | N24: =IF(OR(ISBLANK(H24),ISBLANK(I24)),"", IF(J24="Diferente","Sim",IF(H24="Sim","Sim","Não"))) -> Sim
A25: ACM | B25: Shah, Chirag and White, Ryen W. | C25: From To-Do to Ta-Da: Transforming Task-Focused IR with Generative AI | D25: 2025 | E25: 10.1145/3726302.3730352 | F25: For decades, scholars have emphasized that tasks should be the central focus in Information Retrieval (IR). This point of view holds even more significance with the advent of Generative Artificial Intelligence (GenAI) models, which can, among other capabilities, understand natural language, engage in dialog with users, generate bespoke user interfaces, and power agents to help complete tasks. GenAI presents an unprecedented opportunity to finally realize the potential of tasks in IR, enhance task-focused retrieval and interaction, and create ''magical'' task completion moments for users. In this paper, we explore the rationale and methodology behind this argument. Traditional IR systems support mostly simple tasks. The emergence of GenAI creates an opportunity for IR systems to help users achieve complex tasks and for the IR community to rekindle its interest and demonstrate leadership in this sizable and significant problem space. We underscore the pivotal role of tasks in IR and introduce new evidence supporting the notion that task-centric approaches, abstracted from specific modalities, represent the future of IR. Building on this foundation, we envision the development, utilization, and evaluation of next-generation IR systems. We propose a promising future where IR agents prioritize users, their tasks, and their situations. However, despite their potential to address task-focused and modality-independent IR, agents alone are insufficient. We propose a robust ecosystem around these agents that transcends traditional queries, questions, prompts, and modalities to address users' fundamental needs, tasks, and goals. | G25: agents, generative ai, modalities, tasks | H25: Não | I25: Não | J25: =IF(OR(ISBLANK(H25),ISBLANK(I25)),"",IF(H25<>I25,"Diferente","Igual")) -> Igual | K25: Excluded: Does not sufficiently meet inclusion criteria (AI agent or empirical organizational focus not evident). | L25: Justification: This study is excluded because it fails to satisfy Inclusion Criterion 3. IC 1 & 2 (AI Agents/Organizational Context): The paper discusses the use of Generative AI (GenAI) and IR agents for task completion and task-centric approaches, which is highly relevant. IC 3 (Empirical Evidence): The abstract uses future-oriented language ("We envision the development," "We propose a promising future") and focuses on methodology/rationale/argument. It does not mention presenting any empirical or experimental evidence, or case studies on the implementation or impact of these agents. It is a conceptual/vision paper. | M25: LLM 2 | N25: =IF(OR(ISBLANK(H25),ISBLANK(I25)),"", IF(J25="Diferente","Sim",IF(H25="Sim","Sim","Não"))) -> Não
A26: ACM | B26: Assres, Gebremariam and Bhandari, Guru and Shalaginov, Andrii and Gronli, Tor-Morten and Ghinea, Gheorghita | C26: State-of-the-Art and Challenges of Engineering ML- Enabled Software Systems in the Deep Learning Era | D26: 2025 | E26: 10.1145/3731597 | F26: Emerging from the software crisis of the 1960s, conventional software systems have vastly improved through Software Engineering (SE) practices. Simultaneously, Artificial Intelligence (AI) endeavors to augment or replace human decision-making. In the contemporary landscape, Machine Learning (ML), a subset of AI, leverages extensive data from diverse sources, fostering the development of ML-enabled (intelligent) software systems. While ML is increasingly utilized in conventional software development, the integration of SE practices in developing ML-enabled systems, especially across typical Software Development Life Cycle (SDLC) phases and methodologies in the post-2010 Deep Learning (DL) era, remains underexplored. Our survey of existing literature unveils insights into current practices, emphasizing the interdisciplinary collaboration challenges of developing ML-enabled software, including data quality, ethics, explainability, continuous monitoring and adaptation, and security. The study underscores the imperative for ongoing research and development with focus on data-driven hypotheses, non-functional requirements, established design principles, ML-first integration, automation, specialized testing, and use of agile methods. | G26: Conventional software, ML-enabled software, ML-powered systems, SDLC phases, process areas, software development models | H26: Não | I26: Não | J26: =IF(OR(ISBLANK(H26),ISBLANK(I26)),"",IF(H26<>I26,"Diferente","Igual")) -> Igual | K26: Excluded: Does not sufficiently meet inclusion criteria (AI agent or empirical organizational focus not evident). | L26: Justification: This study is excluded because it fails to satisfy Inclusion Criterion 3 and meets Exclusion Criterion 5. IC 1 & 2 (AI Agents/Organizational Context): While it discusses ML-enabled software systems and challenges (like ethics), the focus is on Software Engineering (SE) practices and the integration of SE in developing ML systems, not the organizational impact/implementation of the AI agents themselves for decision-making or task automation. IC 3 (Empirical Evidence): This is a survey ("Our survey of existing literature unveils insights"), which synthesizes existing literature but does not present new empirical or experimental evidence, or case studies of its own on the organizational impact of the agents. EC 5 (Short Papers/Summarized Formats): Surveys are generally considered secondary studies and are excluded primarily because they do not contain the primary empirical data required by IC 3. The primary reason for exclusion is failure to provide new empirical evidence (IC 3). | M26: LLM 2 | N26: =IF(OR(ISBLANK(H26),ISBLANK(I26)),"", IF(J26="Diferente","Sim",IF(H26="Sim","Sim","Não"))) -> Não
A27: ACM | B27: Huo, ShengXu and Rong, Huigui and Zhou, Yuxuan and Zuo, Hongjia and Liu, Daibo and Li, Zhipan and Wang, Min and Jiang, Hongbo | C27: Crash Scene to Resolution: LLM-based Agents Driven for Efficient Traffic Accident Handling | D27: 2025 | E27: 10.1145/3766899 | F27: Generative agents, capable of simulating human behavior and collaborating on complex tasks, have the potential to revolutionize the investigation of traffic accidents. In this study, we designed TAA (Traffic Accident Agents), an advanced framework based on extended large language models (LLMs) to digitally model urban accident handling procedures and stakeholder interactions. TAA formalizes the roles, responsibilities, and interactions of all stakeholders through natural language encoding, utilizing this knowledge base to orchestrate its execution workflows. Facilitates trusted agent interactions, generates comprehensive reports, and employs memory mechanisms to plan and optimize subsequent actions. We evaluated TAA performance across multiple versions of ChatGPT, focusing on its capabilities to generate reliable interactions, make context-sensitive decisions, maintain extended dialogues, and produce accurate reports in streamlined accident resolution scenarios. Our analysis included evaluations of token consumption and economic costs to ensure scalability and practicality, with TAA achieving 87.9% effectiveness on the GPT 4omini benchmark. Experimental results demonstrate TAA’s successful execution of urban accident handling workflows with maintained informational consistency. The framework shows broad applicability to accident investigation, reconstruction, and archival documentation. This work pioneers the use of generative agents as collaborative human proxies, offering a transformative pathway to advance the future of traffic accident management and investigation. | G27: Traffic Accident Agents, Multi-Agent Collaboration, LLM Agents, Accident handling | H27: Sim | I27: Sim | J27: =IF(OR(ISBLANK(H27),ISBLANK(I27)),"",IF(H27<>I27,"Diferente","Igual")) -> Igual | K27: Included: Addresses AI agents applied to decision-making or automation in organizational contexts with empirical evidence. | L27: Justification: This study strongly aligns with all inclusion criteria and does not meet any exclusion criteria. IC 1 (AI Agents in Organizational Contexts): Designed a framework (TAA) based on extended Large Language Models (LLMs) to digitally model and automate urban accident handling procedures using generative agents for decision-making and collaboration. IC 2 (Organizational Application): Focuses on efficient traffic accident handling and resolution, which is a specific process automation and decision support operation for relevant organizations (e.g., police, insurance, traffic management). IC 3 (Empirical Evidence): Presents experimental results evaluating performance across multiple LLM versions, focusing on capabilities like generating reliable interactions and making context-sensitive decisions, providing empirical evidence. IC 4 (Full Text/Language): The title and abstract are in English, and it's a full-length article published in a conference proceeding (implied full text). EC 3 (Publication Date): Published in 2025 (after 2020). | M27: LLM 2 | N27: =IF(OR(ISBLANK(H27),ISBLANK(I27)),"", IF(J27="Diferente","Sim",IF(H27="Sim","Sim","Não"))) -> Sim
A28: ACM | B28: Namvarpour, Mohammad (Matt) and Razi, Afsaneh | C28: The Art of Talking Machines: A Comprehensive Literature Review of Conversational User Interfaces | D28: 2025 | E28: 10.1145/3719160.3736621 | F28: Conversational User Interfaces (CUIs) enable human-like interactions via voice, text, and multimodal communication, driven by natural language processing and machine learning. Prior literature reviews have primarily focused on specific application domains or design aspects, lacking an integrated, multi-dimensional analysis. This study addresses this gap by providing a structured framework synthesizing CUI research into interface design, system development, and ethical considerations. Our analysis highlights advancements in CUI design, such as dialogue structure, multimodal interactions, and adaptability. It also reveals persistent challenges, including bias in persona design, trust calibration, and data privacy. System development benefits from improvements in NLP, conversation memory, and multilingual capabilities. Ethical considerations, including social bias, user autonomy, and transparency, remain central to discussions on responsible CUI design. By analyzing existing research, we identify key gaps and suggest future directions, including multilingual and culturally adaptive CUIs, privacy-preserving AI techniques, and enhanced reasoning mechanisms for context-aware interactions. | G28: Conversational User Interfaces, CUI, Literature Review, Survey | H28: Não | I28: Não | J28: =IF(OR(ISBLANK(H28),ISBLANK(I28)),"",IF(H28<>I28,"Diferente","Igual")) -> Igual | K28: Excluded: Does not sufficiently meet inclusion criteria (AI agent or empirical organizational focus not evident). | L28: Justification: This study is excluded because it fails to satisfy Inclusion Criterion 3 and meets Exclusion Criterion 5. IC 3 (Empirical Evidence): This is a comprehensive literature review ("providing a structured framework synthesizing CUI research"), which synthesizes existing research but does not present new empirical or experimental evidence, or case studies of its own on the implementation or impact of the agents. EC 5 (Short Papers/Summarized Formats): Literature reviews are generally considered secondary studies and are excluded primarily because they do not contain the primary empirical data required by IC 3. The primary reason for exclusion is failure to provide new empirical evidence (IC 3). | M28: LLM 2 | N28: =IF(OR(ISBLANK(H28),ISBLANK(I28)),"", IF(J28="Diferente","Sim",IF(H28="Sim","Sim","Não"))) -> Não
A29: ACM | B29: Wessel, Mairieli | C29: Enhancing developers’ support on pull requests activities with software bots | D29: 2020 | E29: 10.1145/3368089.3418539 | F29: Software bots are employed to support developers' activities, serving as conduits between developers and other tools. Due to their focus on task automation, bots have become particularly relevant for Open Source Software (OSS) projects hosted on GitHub. While bots are adopted to save development cost, time, and effort, the bots' presence can be disruptive to the community. My research goal is two-fold: (i) identify problems caused by bots that interact in pull requests, and (ii) help bot designers enhance existing bots. Toward this end, we are interviewing maintainers, contributors, and bot developers to understand the problems in the human-bot interaction and how they affect the collaboration in a project. Afterward, we will employ Design Fiction to capture the developers' vision of bots' capabilities, in order to define guidelines for the design of bots on social coding platforms, and derive requirements for a meta-bot to deal with the problems. This work contributes more broadly to the design and use of software bots to enhance developers' collaboration and interaction. | G29: GitHub Bots, Open-source Software, Software Bots | H29: Não | I29: Não | J29: =IF(OR(ISBLANK(H29),ISBLANK(I29)),"",IF(H29<>I29,"Diferente","Igual")) -> Igual | K29: Excluded: Does not sufficiently meet inclusion criteria (AI agent or empirical organizational focus not evident). | L29: Justification: This study is excluded because it meets Exclusion Criterion 5. EC 5 (Short Papers/Summarized Formats): The length and content format of the abstract ("My research goal is two-fold: (i) identify problems... and (ii) help bot designers...") strongly suggest this is a short paper, poster, or extended abstract presenting planned research ("we are interviewing," "we will employ Design Fiction"), not a full article reporting completed findings. It appears to be a doctoral or preliminary research abstract. | M29: LLM 2 | N29: =IF(OR(ISBLANK(H29),ISBLANK(I29)),"", IF(J29="Diferente","Sim",IF(H29="Sim","Sim","Não"))) -> Não
A30: ACM | B30: Wessel, Mairieli | C30: Leveraging Software Bots to Enhance Developers' Collaboration in Online Programming Communities | D30: 2020 | E30: 10.1145/3406865.3418368 | F30: Software bots are applications that are integrated into human communication channels, serving as an interface between users and other tools. Due to their focus on task automation, bots have become particularly relevant for Open Source Software (OSS) projects hosted on GitHub. While bots are adopted to save developers' costs, time, and effort, the interaction of these bots can be disruptive to the community. My research goal is two-fold: (i) identify problems caused by bots that interact in pull requests, and (ii) help bot designers to enhance existing bots, thereby improving the partnership with contributors and maintainers. Toward this end, we are interviewing developers to understand what are the problems on the human-bot interaction and how they affect human collaboration. Afterwards, we will employ Design Fiction to capture the developers' vision of bots' capabilities, in order to define guidelines for the design of bots on social coding platforms, and derive requirements for a meta-bot to deal with the problems. This work contributes more broadly to the design and use of software bots to enhance developers' collaboration and interaction. | G30: github bots, open source software, software bots, software engineering | H30: Não | I30: Não | J30: =IF(OR(ISBLANK(H30),ISBLANK(I30)),"",IF(H30<>I30,"Diferente","Igual")) -> Igual | K30: Excluded: Does not sufficiently meet inclusion criteria (AI agent or empirical organizational focus not evident). | L30: Justification: This study is excluded because it meets Exclusion Criterion 5. EC 5 (Short Papers/Summarized Formats): The length and content format of the abstract ("My research goal is two-fold: (i) identify problems... and (ii) help bot designers...") strongly suggest this is a short paper, poster, or extended abstract presenting planned research ("we are interviewing," "we will employ Design Fiction"), not a full article reporting completed findings. It appears to be a doctoral or preliminary research abstract. (It is also a likely duplicate of the previous entry, EC 4). | M30: LLM 2 | N30: =IF(OR(ISBLANK(H30),ISBLANK(I30)),"", IF(J30="Diferente","Sim",IF(H30="Sim","Sim","Não"))) -> Não
A31: ACM | B31: Alhakamy, A’aeshah | C31: Extended Reality (XR) Toward Building Immersive Solutions: The Key to Unlocking Industry 4.0 | D31: 2024 | E31: 10.1145/3652595 | F31: When developing XR applications for Industry 4.0, it is important to consider the integration of visual displays, hardware components, and multimodal interaction techniques that are compatible with the entire system. The potential use of multimodal interactions in industrial applications has been recognized as a significant factor in enhancing humans’ ability to perform tasks and make informed decisions. To offer a comprehensive analysis of the current advancements in industrial XR, this review presents a structured tutorial that provides answers to the following research questions: (R.Q.1) What are the similarities and differences between XR technologies, including augmented reality (AR), mixed reality (MR), Augmented Virtuality (AV), and virtual reality (VR) under Industry 4.0 consideration? (R.Q.2) What types of visual displays and hardware devices are needed to present XR for Industry 4.0? (R.Q.3) How did the multimodal interaction in XR perceive and relate to Industry 4.0? (R.Q.4) How have modern adaptations of XR technologies dealt with the theme of Industry 4.0? (R.Q.5) How can XR technologies in Industry 4.0 develop their services and usages to be more solution-inclusive? This review showcases various instances that demonstrate XR’s potential to transform how humans interact with the physical world in Industry 4.0. These advancements can increase productivity, reduce costs, and enhance safety. | G31: Extended reality (XR), augmented reality (AR), virtual reality (VR), mixed reality (MR), and augmented virtuality (AV), 4IR, Industry 4.0 | H31: Não | I31: Não | J31: =IF(OR(ISBLANK(H31),ISBLANK(I31)),"",IF(H31<>I31,"Diferente","Igual")) -> Igual | K31: Excluded: Does not sufficiently meet inclusion criteria (AI agent or empirical organizational focus not evident). | L31: Justification: This study is excluded because it fails to satisfy Inclusion Criterion 3 and meets Exclusion Criterion 5. IC 1 & 2 (AI Agents/Organizational Context): The paper focuses on Extended Reality (XR) for Industry 4.0, which involves multimodal interactions to help humans perform tasks and make informed decisions. However, the primary focus is on XR/hardware, and AI agents are not the central object of investigation. IC 3 (Empirical Evidence): This is a structured tutorial/review ("this review presents a structured tutorial"), which answers research questions via synthesis but does not present new empirical or experimental evidence, or case studies of its own on the implementation or impact of the agents. EC 5 (Short Papers/Summarized Formats): Reviews are generally considered secondary studies and are excluded primarily because they do not contain the primary empirical data required by IC 3. The primary reason for exclusion is failure to provide new empirical evidence (IC 3). | M31: LLM 2 | N31: =IF(OR(ISBLANK(H31),ISBLANK(I31)),"", IF(J31="Diferente","Sim",IF(H31="Sim","Sim","Não"))) -> Não
A32: ACM | B32: Yuan, Ming and Yang, Shulin and Gu, Mengdie and Gu, Huijie | C32: Analysis and Research on Book Recommendation Model Based on Big Data | D32: 2021 | E32: 10.1145/3443467.3443723 | F32: In the context of big data, how to define user behavior models and provide personalized reading services for readers by mining large amounts of user data is a problem that the current reading platform needs to optimize urgently. First, we need to analyze the user behavior model to construct the research status and existing problems, in order to provide large data personalized services, targeted user behavior model based on reading platform construction strategies and construction methods, and designs a user logging library is utilized to extract the user interest in dominant and recessive demand ontology of personalized service plan. The user behavior model based on ontology can be technically seamlessly connected with the big data analysis platform, so as to provide real-time and accurate services, which can effectively deal with the challenges of "knowledge trek", "information overload" and "emotional loss" faced by the personalized service of the reading platform in the current big data environment. | G32: Big Data, Linked Data, Ontology, Personalized Service, User Behavior Model | H32: Não | I32: Não | J32: =IF(OR(ISBLANK(H32),ISBLANK(I32)),"",IF(H32<>I32,"Diferente","Igual")) -> Igual | K32: Excluded: Does not sufficiently meet inclusion criteria (AI agent or empirical organizational focus not evident). | L32: The study fails to meet the primary Inclusion Criterion 1 (IC 1) and meets Exclusion Criterion 1 (EC 1). | M32: LLM 2 | N32: =IF(OR(ISBLANK(H32),ISBLANK(I32)),"", IF(J32="Diferente","Sim",IF(H32="Sim","Sim","Não"))) -> Não
A33: ACM | B33: He, Zhuolun and Pu, Yuan and Wu, Haoyuan and Qiu, Tairu and Yu, Bei | C33: Large Language Models for EDA: Future or Mirage? | D33: 2025 | E33: 10.1145/3736167 | F33: In this article, we explore the burgeoning intersection of large language models (LLMs) and electronic design automation (EDA). We critically assess whether LLMs represent a transformative future for EDA or merely a fleeting mirage. By organizing existing research into four critical domains of EDA—code generation, verification and debugging, knowledge representation and retrieval, and optimization/modeling—we provide a comprehensive overview of the current state-of-the-art. The survey concludes with a 5-level roadmap to guide the progressive integration and advancement of LLMs in EDA. Ultimately, this article aims to provide a comprehensive, evidence-based perspective on the role of LLMs in shaping the future of EDA. | G33: Large Language Model | H33: Não | I33: Não | J33: =IF(OR(ISBLANK(H33),ISBLANK(I33)),"",IF(H33<>I33,"Diferente","Igual")) -> Igual | K33: Excluded: Does not sufficiently meet inclusion criteria (AI agent or empirical organizational focus not evident). | L33: The study meets Exclusion Criterion 1 (EC 1) and is weak on Inclusion Criteria 2 (IC 2). | M33: LLM 2 | N33: =IF(OR(ISBLANK(H33),ISBLANK(I33)),"", IF(J33="Diferente","Sim",IF(H33="Sim","Sim","Não"))) -> Não
A34: ACM | B34: Ranade, Nupoor and Saravia, Marly and Johri, Aditya | C34: Using rhetorical strategies to design prompts: a human-in-the-loop approach to make AI useful | D34: 2024 | E34: 10.1007/s00146-024-01905-3 | F34: The growing capabilities of artificial intelligence (AI) word processing models have demonstrated exceptional potential to impact language related tasks and functions. Their fast pace of adoption and probable effect has also given rise to controversy within certain fields. Models, such as GPT-3, are a particular concern for professionals engaged in writing, particularly as their engagement with these technologies is limited due to lack of ability to control their output. Most efforts to maximize and control output rely on a process known as prompt engineering, the construction and modification of the inputted prompt with expectation for certain outputted or desired text. Consequently, prompt engineering has emerged as an important consideration for research and practice. Previous conceptions of prompt engineering have largely focused on technical and logistic modifications to the back-end processing, remaining inaccessible and, still, limited for most users. In this paper, we look to the technical communication field and its methods of text generation—the rhetorical situation—to conceptualize prompt engineering in a more comprehensible way for its users by considering the context and rhetoric. We introduce a framework, consisting of a formula, to prompt engineering, which demands all components of the rhetorical situation be present in the inputted prompt. We present discussions on the future of AI writing models and their use in both professional and educational settings. Ultimately, this discussion and its findings aim to provide a means of integrating agency and writer-centric methods to AI writing tools to advance a more human-in-the-loop approach. As the use of generative AI and especially NLP-based technologies become common across societal functions, the use of prompt engineering will play a crucial role not just in adoption of the technology, but also its productive and responsible use. | G34: Prompt engineering, AI writing, Technical communication, Rhetoric | H34: Não | I34: Não | J34: =IF(OR(ISBLANK(H34),ISBLANK(I34)),"",IF(H34<>I34,"Diferente","Igual")) -> Igual | K34: Excluded: Does not sufficiently meet inclusion criteria (AI agent or empirical organizational focus not evident). | L34: The study fails to meet Inclusion Criteria 2 and 3 (IC 2 and IC 3), and meets Exclusion Criterion 1 (EC 1). | M34: LLM 2 | N34: =IF(OR(ISBLANK(H34),ISBLANK(I34)),"", IF(J34="Diferente","Sim",IF(H34="Sim","Sim","Não"))) -> Não
A35: ACM | B35: Rajesh, K. and Vetrivelan, P. | C35: Comprehensive analysis on 5G and 6G wireless network security and privacy: Comprehensive analysis on 5G and 6G wireless network security and privacy | D35: 2025 | E35: 10.1007/s11235-025-01282-2 | F35: The evolution of 1G to 4G brought significant changes to telecommunication networks but 5G and 6G are not just another generational upgrade. 5G supports real time applications through Ultra Reliable Low Latency Communication, Faster data speeds to enhance Mobile Broadband and Massive Machine Type Communications for connecting numerous devices and, The 6G is expected to support a wider range of applications and services compared to 5G with improved mobility, reliability and autonomous network service it making society more sustainable and energy efficient. Securing these heterogeneous networks is crucial. It requires advanced authentication, authorization and access control methods with enhanced Physical Layer Security, and improved Cyber Physical Systems, Intrusion Detection and Prevention Systems to facilitate secure communication. This research investigates practical demonstrations of security and privacy challenges in 5G and 6G core networks and their connected environments. The study leverages tools such as the NS3 network simulator, Open5GS, QKDNetSim, MATLAB and a proposed Quantum blockchain-based Intrusion Detection System (IDS) framework is designed to preventing adversarial machine learning attacks on network IDS while significantly reducing model training time and improve the model for detect real-time attack detection in the NR (New Radio) Network. | G35: 5G and 6G network security, Quantum-safe 5G and 6G, AI and ML in next-gen wireless security, Blockchain for 5G and 6G | H35: Não | I35: Não | J35: =IF(OR(ISBLANK(H35),ISBLANK(I35)),"",IF(H35<>I35,"Diferente","Igual")) -> Igual | K35: Excluded: Does not sufficiently meet inclusion criteria (AI agent or empirical organizational focus not evident). | L35: The study meets Exclusion Criterion 1 (EC 1). | M35: LLM 2 | N35: =IF(OR(ISBLANK(H35),ISBLANK(I35)),"", IF(J35="Diferente","Sim",IF(H35="Sim","Sim","Não"))) -> Não
... A39: ACM | B39: B\'{e | C39: Artificial intelligence, cyber-threats and Industry 4.0: challenges and opportunities | D39: 2021 | E39: 10.1007/s10462-020-09942-2 | F39: This survey paper discusses opportunities and threats of using artificial intelligence (AI) technology in the manufacturing sector with consideration for offensive and defensive uses of such technology. It starts with an introduction of Industry 4.0 concept and an understanding of AI use in this context. Then provides elements of security principles and detection techniques applied to operational technology (OT) which forms the main attack surface of manufacturing systems. As some intrusion detection systems (IDS) already involve some AI-based techniques, we focus on existing machine-learning and data-mining based techniques in use for intrusion detection. This article presents the major strengths and weaknesses of the main techniques in use. We also discuss an assessment of their relevance for application to OT, from the manufacturer point of view. Another part of the paper introduces the essential drivers and principles of Industry 4.0, providing insights on the advent of AI in manufacturing systems as well as an understanding of the new set of challenges it implies. AI-based techniques for production monitoring, optimisation and control are proposed with insights on several application cases. The related technical, operational and security challenges are discussed and an understanding of the impact of such transition on current security practices is then provided in more details. The final part of the report further develops a vision of security challenges for Industry 4.0. It addresses aspects of orchestration of distributed detection techniques, introduces an approach to adversarial/robust AI development and concludes with human–machine behaviour monitoring requirements. | G39: Intrusion detection systems, Security, Industry 4.0, Artificial intelligence | H39: Não | I39: Não | J39: =IF(OR(ISBLANK(H39),ISBLANK(I39)),"",IF(H39<>I39,"Diferente","Igual")) -> Igual | K39: Excluded: Does not sufficiently meet inclusion criteria (AI agent or empirical organizational focus not evident). | L39: The study meets Exclusion Criterion 1 (EC 1) and is a survey. | M39: LLM 2 | N39: =IF(OR(ISBLANK(H39),ISBLANK(I39)),"", IF(J39="Diferente","Sim",IF(H39="Sim","Sim","Não"))) -> Não
A40: ACM | C40: HRI '24: Companion of the 2024 ACM/IEEE International Conference on Human-Robot Interaction | D40: 2024 | F40: Welcome one and all to the 19th Annual ACM/IEEE International Conference on Human-Robot Interaction (HRI)!We are so pleased to re-welcome the HRI community to Boulder, Colorado, where HRI 2021 would have been held, had the COVID pandemic not interfered. Following up on the successful in-person conference held last year in Sweden, this year's theme is "HRI in the Real World," and focuses on advances that aim to bring human-robot interaction out of the lab and into everyday life.One aspect of this that we are very excited about is the introduction of a robot challenge to the conference activities, where teams from around the world will showcase their research and development via actual, interactive robots in the "real world" of an academic conference. It is our hope that this feature will grow and develop over the coming years into a staple of the HRI conference.This year's HRI conference saw an impressive surge in global interest, with 352 full paper submissions from around the world, marking a significant 40% increase compared to the previous year. These papers were categorized under relevant thematic subcommittees and underwent a double-blind review process, a rebuttal phase, and selective shepherding by the HRI program committee. From this process, 87 outstanding papers (24.7%) were chosen for full presentation at the conference. Reflecting our joint sponsorship with IEEE and ACM, all accepted papers will be accessible in the ACM Digital Library and IEEE Xplore. | H40: Não | I40: Não | J40: =IF(OR(ISBLANK(H40),ISBLANK(I40)),"",IF(H40<>I40,"Diferente","Igual")) -> Igual | K40: Excluded: Does not sufficiently meet inclusion criteria (AI agent or empirical organizational focus not evident). | L40: All conference proceedings meet Exclusion Criterion 5 (EC 5). | M40: LLM 2 | N40: =IF(OR(ISBLANK(H40),ISBLANK(I40)),"", IF(J40="Diferente","Sim",IF(H40="Sim","Sim","Não"))) -> Não
A41: ACM | C41: WWW '25: Companion Proceedings of the ACM on Web Conference 2025 | D41: 2025 | F41: Welcome to The ACM Web Conference 2025 (WWW'25), held from April 28 to May 2, 2025, at the Sydney Convention &amp; Exhibition Centre in Australia. Recognizing the breadth of this year's program, we are publishing two sets of proceedings: one dedicated to research track papers, the Web4Good track, and keynotes; and a companion proceedings featuring the Demo Paper Track, Short Paper Track, PhD Symposium, Special Day, Resource Track, and History of Web sessions. Through this rich assortment of activities, we aim to foster a vibrant community where delegates can share ideas, forge collaborations, and cultivate a sustainable, inclusive environment.Marking its 34th edition, WWW'25 welcomes more than 1,000 industry and academic experts eager to shape the future of Web technologies and applications. The conference logo, depicting the Sydney Harbour Bridge, symbolizes the Web's key function of "connecting" people and information. Originally founded at CERN in 1994 as the International World Wide Web Conference (WWW), this event has long been the leading venue for research, development, standards, and applications related to the Web.Over the years, WWW has introduced important breakthroughs, from The Anatomy of a Large-Scale Web Search Engine in 1998-which heralded Google-to the EigenTrust algorithm in 2003 and the YAGO knowledge base in 2007. In the period between 2024 and 2025, large language models (LLMs) have significantly influenced countless industries and everyday life, prompting fundamental shifts in the Web ecosystem. We anticipate that the research and discussions at this year's conference will spark further breakthroughs in this rapidly evolving field.Continuing the tradition of depth and diversity, WWW'25 accepted 26 workshops and 20 tutorials as pre-conference events. In addition, consistent with previous editions, we feature a Demo Paper Track, Short Paper Track, PhD Symposium, Special Day, Resource Track, History of Web sessions, and Artifact Badging. Some of these are incorporated into the main conference schedule to encourage communication and collaboration among attendees.A commitment to diversity is pivotal to fostering robust, sustainable Web technologies. Our Web4Good track highlights how Web-based tools can address societal challenges, while the Industry Track showcases novel and impactful results from the industrial sector. This year, we have also launched an Emerging World Track to broaden participation from developing countries, as well as a competition track to enhance industry engagement..Organizing WWW'25 has been a true team effort. We sincerely thank the authors who contributed their work, and we extend our gratitude to the program and senior program committees for their dedication to reviewing submissions and offering feedback. We also appreciate the many additional chairs whose efforts ensured that each element of the program ran smoothly. Together, they have helped this conference continue to grow into a premier event for the Web research community.Finally, we would like to thank ACM SIGWEB and our industry sponsors-Meta, Huawei, Google, Baidu, Taobao, JD, and Infinigence-for their generous support, as well as our local government sponsors, Business Event Sydney and the NSW Government. We are equally grateful to our academic partner, the University of Technology Sydney, and the PCO company, ICMSA, for their indispensable help with registration, venue logistics, and social events. Their collective contributions have made the 2025 edition of this conference a resounding success. | H41: Não | I41: Não | J41: =IF(OR(ISBLANK(H41),ISBLANK(I41)),"",IF(H41<>I41,"Diferente","Igual")) -> Igual | K41: Excluded: Does not sufficiently meet inclusion criteria (AI agent or empirical organizational focus not evident). | L41: The primary reason for exclusion is the nature of the submissions. All entries are either Conference Proceedings or Companion Proceedings and their introductory abstracts/forewords. | M41: LLM 2 | N41: =IF(OR(ISBLANK(H41),ISBLANK(I41)),"", IF(J41="Diferente","Sim",IF(H41="Sim","Sim","Não"))) -> Não
A42: ACM | C42: ICPE '25: Companion of the 16th ACM/SPEC International Conference on Performance Engineering | D42: 2025 | F42: Welcome to the 16th ACM/SPEC International Conference of Performance Engineering (ICPE), held in Toronto, Canada, from May 5, 2025, to May 9, 2025. ICPE serves as the premier global forum for showcasing and discussing new concepts, innovations, trends, and experiences in performance engineering.On May 5 and 6, the first two days of the conference, we scheduled five workshops and two tutorials. The workshops cover important topics in performance engineering today. These include cloud computing (HotCloudPerf 2025) and its benchmarking (BID 2025), the benchmarking and load testing of software systems (LTB 2025), performance engineering in the Large Language Models (AIPerfLLM 2025), and the application of performance engineering in both educational and practical contexts (WEPPE 2025). We thank the workshop chairs, Luca Trani and Marios Fokaefs, for arranging a great workshop agenda. On May 5, we have a tutorial on serverless computing entitled "Serverless Orchestration on the Edge-Cloud Continuum: Challenges and Solutions," authored by Reza Farahing and Radu Prodan, while May 6 is dedicated to energy-efficiency benchmarking with the tutorial conducted by Maximilian Meissner, Klaus-Dieter Lange, Aaron Cragin, and Diego Esteves, called "Next Generation Energy-Efficiency Benchmarking - Reliable and Reproducible Efficiency Testing in a Diverse IT-Landscape" and to a hands-on session with the Kieker 2 Observability Framework, authored by Shinhyung Yang, David Georg Reichelt, Reiner Jung, Marcel Hansson, and Wilhelm Hasselbring. We express our gratitude to the tutorial chairs, Vittoria de Nitto Person\`{e | H42: Não | I42: Não | J42: =IF(OR(ISBLANK(H42),ISBLANK(I42)),"",IF(H42<>I42,"Diferente","Igual")) -> Igual | K42: Excluded: Does not sufficiently meet inclusion criteria (AI agent or empirical organizational focus not evident). | L42: The primary reason for exclusion is the nature of the submissions. All entries are either Conference Proceedings or Companion Proceedings and their introductory abstracts/forewords. | M42: LLM 2 | N42: =IF(OR(ISBLANK(H42),ISBLANK(I42)),"", IF(J42="Diferente","Sim",IF(H42="Sim","Sim","Não"))) -> Não
A43: ACM | C43: SIGIR '25: Proceedings of the 48th International ACM SIGIR Conference on Research and Development in Information Retrieval | D43: 2025 | F43: It is our great pleasure to welcome you to the 48th Annual International ACM SIGIR Conference on Research and Development in Information Retrieval (ACM SIGIR 2025), taking place in Padova, Italy, from July 13th to July 18th, 2025.This year's conference continues its tradition of being the premier international forum for presenting cutting-edge research and showcasing innovative systems and techniques in the broad field of Information Retrieval.SIGIR 2025 is an in-person conference. We believe that holding the conference in person offers significant advantages, including richer opportunities for direct engagement and networking, a more dynamic exchange of research ideas, and a more welcoming environment for newcomers. To accommodate those who, in exceptional cases, are unable to attend in person, we have arranged for the option of proxy presenters (i.e. a qualified person presents on their behalf).This year's conference spans six days, beginning with a day dedicated to the Doctoral Consortium and Tutorial presentations. The following three days feature sessions comprising three Keynote Talks, full papers, short papers, resource and reproducibility papers, perspective papers, lowresources environments papers, system demonstrations, and an industry track (SIRIP). The program also features two Women in IR (WIR) activities (a panel and a poster session). Finally, the last day is devoted to Workshops aimed at fostering discussion and encouraging collaboration on emerging research topics in Information Retrieval, as well as to the LiveRag challenge, organized by the Technology Innovation Institute, and focused on Retrieval Augmented Generation. On Friday the 18th the ICTIR 2025 Conference takes place.Social highlights include a welcome reception, a conference dinner, a student luncheon and student party, as well as the WIR reception and the ICTIR Social Dinner.The SIGIR 2025 technical program is highlighted by three keynote presentations delivered by esteemed speakers, to whom we extend our sincere gratitude: Stephen Robertson (Girton College, Cambridge, UK), Iryna Gurevych (Technical University of Darmstadt, Germany), and Ophir Frieder (Georgetown University, Washington DC, USA). | H43: Não | I43: Não | J43: =IF(OR(ISBLANK(H43),ISBLANK(I43)),"",IF(H43<>I43,"Diferente","Igual")) -> Igual | K43: Excluded: Does not sufficiently meet inclusion criteria (AI agent or empirical organizational focus not evident). | L43: The primary reason for exclusion is the nature of the submissions. All entries are either Conference Proceedings or Companion Proceedings and their introductory abstracts/forewords. | M43: LLM 2 | N43: =IF(OR(ISBLANK(H43),ISBLANK(I43)),"", IF(J43="Diferente","Sim",IF(H43="Sim","Sim","Não"))) -> Não
A44: ACM | C44: HRI '24: Proceedings of the 2024 ACM/IEEE International Conference on Human-Robot Interaction | D44: 2024 | F44: Welcome one and all to the 19th Annual ACM/IEEE International Conference on Human-Robot Interaction (HRI)!We are so pleased to re-welcome the HRI community to Boulder, Colorado, where HRI 2021 would have been held, had the COVID pandemic not interfered. Following up on the successful in-person conference held last year in Sweden, this year's theme is "HRI in the Real World," and focuses on advances that aim to bring human-robot interaction out of the lab and into everyday life.One aspect of this that we are very excited about is the introduction of a robot challenge to the conference activities, where teams from around the world will showcase their research and development via actual, interactive robots in the "real world" of an academic conference. It is our hope that this feature will grow and develop over the coming years into a staple of the HRI conference.This year's HRI conference saw an impressive surge in global interest, with 352 full paper submissions from around the world, marking a significant 40% increase compared to the previous year. These papers were categorized under relevant thematic subcommittees and underwent a double-blind review process, a rebuttal phase, and selective shepherding by the HRI program committee. From this process, 87 outstanding papers (24.7%) were chosen for full presentation at the conference. Reflecting our joint sponsorship with IEEE and ACM, all accepted papers will be accessible in the ACM Digital Library and IEEE Xplore. | H44: Não | I44: Não | J44: =IF(OR(ISBLANK(H44),ISBLANK(I44)),"",IF(H44<>I44,"Diferente","Igual")) -> Igual | K44: Excluded: Does not sufficiently meet inclusion criteria (AI agent or empirical organizational focus not evident). | L44: The primary reason for exclusion is the nature of the submissions. All entries are either Conference Proceedings or Companion Proceedings and their introductory abstracts/forewords. | M44: LLM 2 | N44: =IF(OR(ISBLANK(H44),ISBLANK(I44)),"", IF(J44="Diferente","Sim",IF(H44="Sim","Sim","Não"))) -> Não
A45: ACM | C45: UbiComp '24: Companion of the 2024 on ACM International Joint Conference on Pervasive and Ubiquitous Computing | D45: 2024 | F45: Welcome to UbiComp/ISWC 2024, the companion program of two premier conferences: The 2024 ACM International Joint Conference on Pervasive and Ubiquitous Computing (UbiComp 2024) and the 2024 International Symposium on Wearable Computers (ISWC 2024). UbiComp and ISWC are premier interdisciplinary venues for international researchers, designers, developers, practitioners and educators in the field to present and discuss novel and impactful research in interactive, mobile, wearable and ubiquitous computing. The companion program has traditionally been a very important part of the UbiComp/ISWC conference series.UbiComp/ISWC 2024 is held from October 5 to 9, 2024 in Melbourne, Australia. Originally, UbiComp/ISWC was scheduled to take place in Melbourne in 2021. However, due to the significant impact of COVID-19, our community decided to postpone conferences taking place in their traditional form until last year, when UbiComp took place as an in-person event in Mexico. Now, in 2024 we look to consolidate the strength and ties in our community by having another fully in-person event and hoping to welcome a new generation of researchers to meet and explore the wonderful people that make up our community. | H45: Não | I45: Não | J45: =IF(OR(ISBLANK(H45),ISBLANK(I45)),"",IF(H45<>I45,"Diferente","Igual")) -> Igual | K45: Excluded: Does not sufficiently meet inclusion criteria (AI agent or empirical organizational focus not evident). | L45: The primary reason for exclusion is the nature of the submissions. All entries are either Conference Proceedings or Companion Proceedings and their introductory abstracts/forewords. | M45: LLM 2 | N45: =IF(OR(ISBLANK(H45),ISBLANK(I45)),"", IF(J45="Diferente","Sim",IF(H45="Sim","Sim","Não"))) -> Não
A46: ACM | C46: WSDM '25: Proceedings of the Eighteenth ACM International Conference on Web Search and Data Mining | D46: 2025 | F46: Welcome to the 18th ACM International Conference on Web and Data Mining, this time taking place in Hannover, Germany.Many volunteers have helped to provide excellent content for the conference, most of all the 3 PC Chairs, Meeyoung Cha (Max Planck Institute for Security and Privacy in Germany), Francine Moens (KU Leuven, Belgium) and Marc Najork (Google DeepMind, USA), who selected more than 100 papers from over 600 submissions for presentation at the conference.This exciting WSDM 2025 main conference program was extended by interesting demonstrations like Lightning IR for fine-tuning and inference of transformer-based language models for information retrieval, WildlifeLookup, a chatbot designed to facilitate wildlife management and Ventana a la Verdad, a chatbot for navigating Colombian civil conflict archives. Several workshops ranging from language models to trust and verification on the Web complemented this program and provided important opportunities for the discussion of exciting new ideas and approaches.WSDM Cup 2025 challenged more than 1000 competitors to create useful and efficient auto-rater models that can accurately reflect human evaluations. This competition focused on the creation of multilingual auto-rater models using chatbot arena data, with exciting solutions. The WSDM 2025 Industry Day featured talks from leading companies on practical applications of web search and data mining. Some notable examples included zero-shot image moderation in Google Ads, advancing Voice AI for E-commerce at Amazon, and Fact-checking of multilingual podcasts. Finally, WSDM Day talks focused on medical research questions and topics, applying language models, knowledge graphs and other AI based approaches.For participants aiming to enter new research areas, the WSDM 2025 tutorials covered a broad range of topics, including Robust Information Retrieval, Building Trustworthy AI Models for Medicine, Unifying Bias and Unfairness in Information Retrieval in the LLM Era, Advances in Vector Search and quite a few more. And finally, three excellent invited speakers (Slav Petrov from Google DeepMind and co-lead on Gemini, Roberto Navigli from Sapienza University and Babelscape and Mario Fritz from CISPA) provided exciting insights into the state of AI, about what large language models really understand, as well as privacy and security aspects of neural models. | H46: Sim | I46: Não | J46: =IF(OR(ISBLANK(H46),ISBLANK(I46)),"",IF(H46<>I46,"Diferente","Igual")) -> Diferente | K46: Included: Addresses AI agents applied to decision-making or automation in organizational contexts with empirical evidence. | L46: The primary reason for exclusion is the nature of the submissions. All entries are either Conference Proceedings or Companion Proceedings and their introductory abstracts/forewords. | M46: LLM 2 | N46: =IF(OR(ISBLANK(H46),ISBLANK(I46)),"", IF(J46="Diferente","Sim",IF(H46="Sim","Sim","Não"))) -> Sim
A47: ACM | C47: SIGIR '24: Proceedings of the 47th International ACM SIGIR Conference on Research and Development in Information Retrieval | D47: 2024 | F47: Welcome to the 47th Annual International ACM SIGIR Conference on Research and Development in Information Retrieval (SIGIR 2024), taking place in Washington D.C., USA, from July 14 to 18, 2024.SIGIR serves as the foremost international forum for the presentation of groundbreaking research findings, the demonstration of innovative systems and techniques, and the exploration of forwardthinking research directions in the field of information retrieval.This year's SIGIR is an in-person conference. We believe that an in-person conference is beneficial for several reasons: it fosters direct engagement and networking opportunities, enhances the exchange of research ideas, contributes to a more dynamic and productive conference experience, and nurtures our research community by welcoming newcomers, providing them with the opportunity to become acquainted with SIGIR traditions. This decision has not been made lightly. We understand the challenges that can pose in the aftermath of a pandemic and amidst the uncertainties of the world around us. To accommodate those who cannot attend, we have implemented a series of measures such as proxy presenters, livestreaming, and recording sessions. These steps are taken to ensure that everyone has access to the valuable content that the conference offers. | H47: Não | I47: Não | J47: =IF(OR(ISBLANK(H47),ISBLANK(I47)),"",IF(H47<>I47,"Diferente","Igual")) -> Igual | K47: Excluded: Does not sufficiently meet inclusion criteria (AI agent or empirical organizational focus not evident). | L47: The primary reason for exclusion is the nature of the submissions. All entries are either Conference Proceedings or Companion Proceedings and their introductory abstracts/forewords. | M47: LLM 2 | N47: =IF(OR(ISBLANK(H47),ISBLANK(I47)),"", IF(J47="Diferente","Sim",IF(H47="Sim","Sim","Não"))) -> Não
A48: ACM | C48: WWW '25: Proceedings of the ACM on Web Conference 2025 | D48: 2025 | F48: The 2025 ACM Web Conference (WWW '25) took place from April 28 to May 2, 2025, in the Sydney Convention &amp; Exhibition Centre, Australia. Its logo, featuring the Sydney Harbour Bridge, symbolizes the core "connecting" function of the Web. Formerly known as the International World Wide Web Conference (WWW), this event originated at CERN in 1994 and has long served as the premier venue for presenting and discussing research, development, standards, and applications related to the Web.The 2025 ACM Web Conference (WWW'25) took place from April 28 to May 2, 2025, in the Sydney Convention &amp; Exhibition Centre, Australia. Its logo, featuring the Sydney Harbour Bridge, symbolizes the core "connecting" function of the Web. Formerly known as the International World Wide Web Conference (WWW), this event originated at CERN in 1994 and has long served as the premier venue for presenting and discussing research, development, standards, and applications related to the Web.Between 2024 and 2025, large language models (LLMs) significantly impacted nearly every industry and many aspects of daily life, prompting transformations in the Web's ecosystem. Acknowledging the importance of LLMs in advancing Web technologies, the call for papers (CFP) across ten research tracks was slightly modified. Three program chairs - Liane Lewin-Eytan, Helen Huang, and Elad Yom-Tov - led the program committee, which used OpenReview to evaluate and accept the research track papers. | H48: Não | I48: Não | J48: =IF(OR(ISBLANK(H48),ISBLANK(I48)),"",IF(H48<>I48,"Diferente","Igual")) -> Igual | K48: Excluded: Does not sufficiently meet inclusion criteria (AI agent or empirical organizational focus not evident). | L48: The primary reason for exclusion is the nature of the submissions. All entries are either Conference Proceedings or Companion Proceedings and their introductory abstracts/forewords. | M48: LLM 2 | N48: =IF(OR(ISBLANK(H48),ISBLANK(I48)),"", IF(J48="Diferente","Sim",IF(H48="Sim","Sim","Não"))) -> Não
A49: ACM | C49: WSDM '24: Proceedings of the 17th ACM International Conference on Web Search and Data Mining | D49: 2024 | F49: It is our great pleasure to welcome you to the 17th ACM International Conference on Web Search and Data Mining - WSDM 2024. WSDM is one of the premier conferences in the fields of web search and data mining, with a dynamic and growing community from academia and industry. After two years of virtual conferences and in-person conferences in Singapore, the 2024 edition is an in-person conference with virtual elements. We hope you enjoy the conference at the "Centro Internacional de Congresos de Yucatan (CIC)" in Merida from March 4 to March 8, 2024.We are excited to kick off the program with a dynamic mix of Tutorials and Industry Day. Our seven tutorials will cover a broad range of search and data mining topics. Industry Day will provide valuable insights from leaders at major technology companies. The core technical program continues WSDM's tradition of a single-track format, featuring 109 thought-provoking papers from both academic and industry experts. We're honored to have inspiring keynote speakers each day: Nicolas Christin (CMU), Elizabeth Reid (Google), and Saiph Savage (Civic A.I. Lab). Additionally, 17 interactive demonstrations will showcase the latest prototypes and systems. The final day offers a stimulating Doctoral Consortium and six engaging workshops on topics including integrity in social networks, large language model for society, psychology-informed information access system, interactive and scalable information retrieval system and machine learning on graphs. WSDM 2024 proudly presents WSDM day on information retrieval and Web in the region. WSDM Cup Day highlights finalists' presentations addressing challenges in Conversational Multi-Doc QA. This diverse and stimulating program promises to be an enriching experience for all!. | H49: Não | I49: Não | J49: =IF(OR(ISBLANK(H49),ISBLANK(I49)),"",IF(H49<>I49,"Diferente","Igual")) -> Igual | K49: Excluded: Does not sufficiently meet inclusion criteria (AI agent or empirical organizational focus not evident). | L49: The primary reason for exclusion is the nature of the submissions. All entries are either Conference Proceedings or Companion Proceedings and their introductory abstracts/forewords. | M49: LLM 2 | N49: =IF(OR(ISBLANK(H49),ISBLANK(I49)),"", IF(J49="Diferente","Sim",IF(H49="Sim","Sim","Não"))) -> Não
A50: ACM | C50: CCS '24: Proceedings of the 2024 on ACM SIGSAC Conference on Computer and Communications Security | D50: 2024 | F50: It is with great enthusiasm that we, on behalf of the Organizing Committee, invite you to join us for the 31st ACM SIGSAC Conference on Computer and Communications Security (CCS), a premier security and privacy conference where researchers, practitioners, and educators come together to present, learn, and debate research, innovation, and trends in the field of Computer and Communications Security and Privacy.This year, we are proud to introduce our conference theme to be "Inclusion, Mentorship, Community." These three pillars reflect our collective commitment to fostering a vibrant, supportive, and forwardthinking environment within the CCS community. Particularly, we host our inaugural Doctoral Symposium, which offers PhD students a unique platform to receive timely, constructive feedback on their dissertation research from leading experts in our community. Additionally, our first-ever Diversity, Equity, and Inclusion (DEI) Workshop is designed to cultivate a culture that embraces diversity and champions equity in our field. Moreover, understanding the importance of guidance and support, we have organized panels focusing on Student Mentoring, Faculty Mentoring, and Public Service. These panels are designed to facilitate mentorship connections, share valuable experiences, and encourage service that extends the impact of our work beyond academia. These new initiatives are also opportunities to strengthen the bonds within our CCS community.Regarding the main conference, this year's main conference is our largest ever, featuring 328 paper presentations that showcase the latest research and developments in our field. We are also honored to have two distinguished keynote speakers: Dr. Dan Boneh and Dr. Gene Tsudik, who will share their invaluable insights and perspectives on pressing topics in security and privacy. Additionally, 18 specialized workshops will take place on the pre-conference and post-conference days, providing platforms for focused discussions and collaborations on numerous specialized topics. | H50: Não | I50: Não | J50: =IF(OR(ISBLANK(H50),ISBLANK(I50)),"",IF(H50<>I50,"Diferente","Igual")) -> Igual | K50: Excluded: Does not sufficiently meet inclusion criteria (AI agent or empirical organizational focus not evident). | L50: The primary reason for exclusion is the nature of the submissions. All entries are either Conference Proceedings or Companion Proceedings and their introductory abstracts/forewords. | M50: LLM 2 | N50: =IF(OR(ISBLANK(H50),ISBLANK(I50)),"", IF(J50="Diferente","Sim",IF(H50="Sim","Sim","Não"))) -> Não
A51: ACM | C51: MM '24: Proceedings of the 32nd ACM International Conference on Multimedia | D51: 2024 | F51: We are delighted to welcome you to Melbourne, Australia for ACM Multimedia 2024, the 32nd ACM International Conference on Multimedia. ACM Multimedia is the premier international conference series in the area of multimedia within the field of computer science. Since 1993, ACM Multimedia has been bringing together worldwide researchers and practitioners from academia and industry to present their innovative research and to discuss recent advancements in multimedia.For the first time since the end of the COVID-19 pandemic, this year's conference returns to the Asia-Pacific region and resumes as a full-fledged, inperson event. With no travel restrictions or significant visa challenges, we are excited to once again experience the warmth of face-to-face gatherings, where we can reconnect with colleagues and friends.The enthusiasm and support from the community have been incredible. ACM Multimedia 2024 received over 4,300 main conference submissions, accepting more than 1,100 papers (please refer to the TPC Chairs' message for details). In addition, 10 Grand Challenges were selected from 22 submissions, 18 workshops from 30 submissions, and 8 tutorials from 13 proposals. We've prepared an exciting five-day program: workshops, grand challenges, and tutorials will be held on the 1st and 5th days, with the main conference occupying the middle three days. All accepted papers will be accessible online prior to the conference, and we are working to ensure proceedings are available through the ACM Digital Library around the conference period.This year's conference features three distinguished academic keynote speeches, several prestigious SIGMM award talks, a panel discussion on Generative AI in Multimedia, a refreshed Brave New Idea (BNI) session, and our inaugural industry program.The opening keynote will be delivered by Prof. Pascale Fung from HKUST, a Fellow of AAAI, ACL, and IEEE. Her talk will explore the pressing topic of Agents in the Large Language Model (LLM) Era. Prof. Judy Kay from the University of Sydney, a renowned expert in HCI, user modeling, and ubiquitous computing, will give the second keynote on how to empower individuals to harness and control their multimodal data. The final academic keynote will be presented by Prof. Jiebo Luo from the University of Rochester, a Fellow of ACM, AAAI, IEEE, SPIE, and IAPR, as well as a member of Academia Europaea and the US National Academy of Inventors. He will discuss leveraging LLMs as social multimedia analysis engines.This year, we continue using OpenReview to ensure an open and transparent review process. Thanks to the exceptional efforts of the technical program committee, every paper received at least three reviews before the review announcement. The BNI track has also revamped its review process to align with the main conference, promoting visionary papers. Additionally, we are excited to introduce the industry program to ACM Multimedia for the first time, featuring industry keynote speeches, expert talks, and demonstrations (please refer to the industry chairs' message for further details).We are also committed to making the conference inclusive and accessible. To support students with financial constraints, we have awarded travel grants to at least 25 students from the ACM Multimedia 2024 budget, with an additional 20+ students receiving SIGMM travel grants. Over 20 local students have also been recruited as volunteers, benefiting from complimentary registration. Furthermore, we have arranged childcare facilities to accommodate attendees with young children. A welcome reception will take place on the 2nd day of the conference, followed by a gala dinner on the 3rd day, featuring exciting cultural performances.We hope you find this year's program engaging and thought-provoking and that it offers valuable opportunities to exchange ideas with fellow researchers and practitioners from around the globe. We also encourage you to take time to explore the beautiful city of Melbourne and its surrounding regions. | H51: Não | I51: Não | J51: =IF(OR(ISBLANK(H51),ISBLANK(I51)),"",IF(H51<>I51,"Diferente","Igual")) -> Igual | K51: Excluded: Does not sufficiently meet inclusion criteria (AI agent or empirical organizational focus not evident). | L51: The entry meets Exclusion Criterion 5 (EC 5). | M51: LLM 2 | N51: =IF(OR(ISBLANK(H51),ISBLANK(I51)),"", IF(J51="Diferente","Sim",IF(H51="Sim","Sim","Não"))) -> Não
A52: ACM | C52: ASPLOS '24: Proceedings of the 29th ACM International Conference on Architectural Support for Programming Languages and Operating Systems, Volume 3 | D52: 2024 | F52: Welcome to the third volume of ASPLOS'24: the 29th ACM International Conference on Architectural Support for Programming Languages and Operating Systems. This document is mostly dedicated to the 2024 fall cycle but also provides some statistics summarizing all three cycles.We introduced several notable changes to ASPLOS this year, most of which were discussed in our previous messages from program chairs in Volume 1 and 2, including: (1) significantly increasing the program committee size to over 220 members (more than twice the size of last year); (2) foregoing synchronous program committee (PC) meetings and instead making all decisions online; (3) overhauling the review assignment process; (4) developing an automated submission format violation identifier script that uncovers, e.g., disallowed vertical space manipulations that "squeeze" space; (5) introducing the new ASPLOS role of Program Vice Chairs to cope with the increased number of submissions and the added load caused by foregoing synchronous program committee; and (6) characterizing a systematic problem that ASPLOS is facing in reviewing quantum computing submissions, describing how we addressed it and highlighting how we believe that it should be handled in the future.Assuming readers have read our previous messages, here, we will only describe differences between the current cycle and the previous ones. These include: (1) Finally unifying submission and acceptance paper formatting instructions (forgoing the `jpaper' class) to rid authors of accepted papers from the need to reformat; (2) Describing the methodology we employed to select best papers, which we believe ensures quality and hope will persist; and (3) Reporting the ethical incidents we encountered and how we handled them. In the final, fourth volume, when the outcome of the ASPLOS'24 fall major revisions will become known, we plan to conduct a broader analysis of all the data we have gathered throughout the year.Following are some key statistics of the fall cycle: 340 submissions were finalized (43% more than last year's fall count and 17% less than our summer cycle) of which 111 are related to accelerators/FPGAs/GPUs, 105 to machine learning, 54 to security, 50 to datacenter/cloud and 50 to storage/memory; 183 (54%) submissions were promoted to the second review round; 39 (11.5%) papers were accepted (of which 19 were awarded artifact evaluation badges); 33 (9.7%) submissions were allowed to submit major revisions and are currently under review (these will be addressed in the fourth volume of ASPLOS'24 and will be presented in ASPLOS'25 if accepted); 1,368 reviews were uploaded; and 4,949 comments were generated during online discussions, of which 4,070 were dedicated to the submissions that made it to the second review round.This year, in the submission form, we asked authors to specify which of the three ASPLOS research areas are related to their submitted work. Analyzing this data revealed that 80%, 39%, and 29% of the submissions are categorized by their authors as related to architecture, operating systems, and programming languages, respectively, generating the highest difference we have observed across the cycles between architecture and the other two. About 46% of the fall submissions are "interdisciplinary," namely, were associated with two or more of the three areas.Overall, throughout all the ASPLOS'24 cycles, we received 922 submissions, constituting a 1.54x increase compared to last year. Our reviewers submitted a total of 3,634 reviews containing more than 2.6 million words, and we also generated 12,655 online comments consisting of nearly 1.2 million words. As planned, PC members submitted an average of 15.7 reviews and a median of 15, and external review committee (ERC) members submitted an average of 4.7 and a median of 5.We accepted 170 papers thus far, written by 1100 authors, leading to an 18.4% acceptance rate, with the aforementioned 33 major revisions still under review. Assuming that the revision acceptance rate will be similar to that of previous cycles, we estimate that ASPLOS'24 will accept nearly 200 (!) papers, namely, 21%–22% of the submissions.The ASPLOS'24 program consists of 193 papers: the 170 papers we accepted thus far and, in addition, 23 major revisions from the fall cycle of ASPLOS'23, which were re-reviewed and accepted. The full details are available in the PDF of the front matter. | H52: Não | I52: Não | J52: =IF(OR(ISBLANK(H52),ISBLANK(I52)),"",IF(H52<>I52,"Diferente","Igual")) -> Igual | K52: Excluded: Does not sufficiently meet inclusion criteria (AI agent or empirical organizational focus not evident). | L52: The entry meets Exclusion Criterion 5 (EC 5). | M52: LLM 2 | N52: =IF(OR(ISBLANK(H52),ISBLANK(I52)),"", IF(J52="Diferente","Sim",IF(H52="Sim","Sim","Não"))) -> Não
A53: Scopus | B53: Khan, M.A.; Rahman, A.; Mahmud, F.U.; Bishnu, K.K.; Ahmed, M.; Mridha, M.F.; Aung, Z. | C53: A systematic review of AI-driven business models for advancing Sustainable Development Goals | D53: 2025 | F53: Artificial Intelligence (AI) is changing how businesses operate and contributing to the United Nations Sustainable Development Goals (SDGs). This paper reviews how AI-driven business models support economic growth, environmental protection, and social well-being. It examines key technologies like machine learning, natural language processing, computer vision, and autonomous systems, and their use in industries such as healthcare, energy, and logistics. This paper introduces a comprehensive taxonomy that classifies AI technologies according to their roles in sustainable business models. The taxonomy outlines how different technologies contribute to data analysis, decision-making, process automation, and human-AI interaction, helping to explain how AI creates, delivers, and captures value aligned with the SDGs. The study also reviews recent works, outlining their achievements and limitations, particularly for underexplored SDGs. Common challenges, including ethical issues, resource limitations, and policy gaps are identified. The paper highlights the need for AI frameworks that are scalable, transparent, and inclusive. Finally, it suggests directions for future research, focusing on collaboration, innovative methods, and addressing current gaps to harness AI's potential for sustainable development. © 2025 Elsevier B.V., All rights reserved. | G53: Economics; Environmental protection; Learning systems; Machine learning; Sustainable development goals; Artificial intelligence-driven business model; Business models; Economic growths; Key technologies; Machine-learning; Natural languages; Social well-being; Systematic Review; United Nations; Sustainable development | H53: Não | I53: Não | J53: =IF(OR(ISBLANK(H53),ISBLANK(I53)),"",IF(H53<>I53,"Diferente","Igual")) -> Igual | K53: Justification: secondary/SLR/agenda study – does not present primary empirical evidence of AI agent implementation in organizational customer service, process automation, or decision support (fails IC3). | L53: The study meets Exclusion Criterion 5 (EC 5) and Exclusion Criterion 1 (EC 1) in spirit. | M53: LLM 2 | N53: =IF(OR(ISBLANK(H53),ISBLANK(I53)),"", IF(J53="Diferente","Sim",IF(H53="Sim","Sim","Não"))) -> Não
A54: Scopus | B54: Park, C.; Moon, H.; Shin, J. | C54: Do restaurant customers and owners differ in their preferences for serving robots? A choice experiment and latent class approach | D54: 2025 | F54: Serving robots are increasingly being adopted by restaurants to address labor shortages and improve operational efficiency. These robots offer a range of benefits to restaurant owners, including increased productivity and a novel customer experience. However, there are barriers to adopting these technologies, including the digital literacy gap, emotional resistance, and social concerns regarding the impact of automation. Nevertheless, most existing research has focused on customer acceptance of serving robots, overlooking the perspectives of restaurant owners, who are the actual decision makers driving their adoption. This study addresses this gap by analyzing the heterogeneous preferences of customers and restaurant owners regarding serving robot types. Using a discrete choice experiment (DCE) and latent class analysis (LCA), this study identified two segments in each group. Customers were technology-progressive (43.6 %) or technology-conservative (56.4 %); owners were interaction-oriented (60.3 %) or appearance-oriented (39.7 %). The results showed that customers generally prefer non-humanoid robots, whereas owners favor fixed-type or humanoid robots. Notably, customers were the least likely to accept humanoid robots, indicating a potential “uncanny valley” effect. These divergent preferences suggest that successfully introducing serving robots to restaurants requires a strategic alignment between customer experience and owner priorities. By comparing these two stakeholder groups, this study provides practical insights for restaurant owners and robot manufacturers seeking to facilitate the effective introduction of serving robots in customer-facing environments. © 2025 Elsevier B.V., All rights reserved. | G54: Behavioral research; Decision making; Human robot interaction; Man machine systems; Sales; Choice experiments; Customer experience; Heterogeneous preference; Humanoid robot; Humans-robot interactions; Labor shortages; Latent class; Operational efficiencies; Serving robot; Uncanny valley; Anthropomorphic robots; discrete choice analysis; food market; preference behavior; robotics; stakeholder; valley | H54: Não | I54: Sim | J54: =IF(OR(ISBLANK(H54),ISBLANK(I54)),"",IF(H54<>I54,"Diferente","Igual")) -> Diferente | K54: Justification: focuses on service robots/consumer acceptance, not on AI agents (LLMs, chatbots, multi-agent or RL) applied to organizational decision-making or task automation (fails IC1/IC2). | L54: Strong alignment with all inclusion criteria and no (relevant) exclusion criteria met. | M54: LLM 1 | N54: =IF(OR(ISBLANK(H54),ISBLANK(I54)),"", IF(J54="Diferente","Sim",IF(H54="Sim","Sim","Não"))) -> Sim
A55: Scopus | B55: Bi, C.; Cui, X.; Sun, Z.; Jin, Y. | C55: Thinking AI or feeling AI? The effect of AI on consumers’ willingness to purchase healthy food from the perspective of nudge | D55: 2025 | F55: The application of AI technologies in influencing consumers’ willingness to purchase healthy food is becoming increasingly prevalent. Significant differences have been observed in the service characteristics of different AI types (thinking AI vs. feeling AI) and consumers’ decision-making pathways across various consumption contexts (public vs. personal). In response to this, the present study systematically explores the interactive effects of AI type and consumption context on consumers’ willingness to purchase healthy food based on nudge theory, employing two 2 × 2 between-subject experiments. Study 1 recruited 120 valid participants, who were randomly assigned to either a public or personal consumption context. Their willingness to purchase healthy food was measured using a seven-point Likert scale to examine the interaction between AI type and consumption context. Study 2 further investigated the mediating roles of cognitive and affective responses in this interaction effect. Additionally, robustness checks were conducted by modifying AI product materials and repeating the experiment to ensure the reliability of the findings. This study unveils the interaction effect between AI type and consumption context, as well as its underlying mediating mechanism, thereby expanding the theoretical framework of research on health food consumption behavior. Furthermore, the findings provide practical insights for businesses to develop precise AI-driven health food marketing strategies. © 2025 Elsevier B.V., All rights reserved. | H55: Não | I55: Sim | J55: =IF(OR(ISBLANK(H55),ISBLANK(I55)),"",IF(H55<>I55,"Diferente","Igual")) -> Diferente | K55: Justification: title does not provide enough evidence that the study (i) investigates AI agents for organizational decision-making or process automation, (ii) targets customer service/decision support, and (iii) reports empirical/case evidence – at least one IC is not satisfied, so score = 0. | L55: Strong alignment with all inclusion criteria and no (relevant) exclusion criteria met. | M55: LLM 1 | N55: =IF(OR(ISBLANK(H55),ISBLANK(I55)),"", IF(J55="Diferente","Sim",IF(H55="Sim","Sim","Não"))) -> Sim
A56: Scopus | B56: Gavrila Gavrila, S.; de Lucas López, A.P.; Verdugo Molano, C. | C56: AI automation at an unprecedented scale: mapping its adoption and specialisation | D56: 2025 | F56: This paper investigates how Artificial Intelligence (AI) goes beyond traditional technological roles to drive transformation across industries, organisations, and society. By analysing 2188 academic papers from the arXiv platform (from 2018 until 2025), the study highlights the unexpectedly widespread adoption of AI and its increasing specialisation in tasks and organisational functions. The findings reveal AI's potential to foster innovation, enhance productivity, and address complex challenges. While the focus on academic sources and the exclusion of regional contexts present certain limitations, this research provides critical insights into AI's evolving role and its implications for businesses, employees, and the conduct of government. Purpose/aims of the paper: This study explores how AI has evolved from technical applications to become a key driver of innovation and knowledge creation. It investigates AI's penetration across industries, organisational areas, and tasks, focusing on its ability to solve complex challenges, reshape business workflows, and enable strategic decision-making in diverse contexts. Research methodology: The research employed secondary data analysis of 2188 full-text academic papers sourced from the arXiv platform. Structured keyword extraction, conducted using Large Language Models, identified patterns and relationships between industries, organisational areas, and tasks. Additionally, trends in AI adoption, specialisation, and integration were examined to uncover its transformative impact on organisations and knowledge systems. Findings/conclusions: The findings reveal AI's significant penetration into industries and its increasing specialisation in organisational areas and tasks. Beyond automation, AI fosters task-specific solutions and innovation, addressing organisational challenges and improving productivity. These findings underscore AI's transformative potential to redefine business practices, enhance collaboration, and drive societal progress by pushing the boundaries of innovation and knowledge creation. Discussion: AI's influence has expanded far beyond technical functions, establishing itself as a strategic tool for innovation, cross-disciplinary problem-solving, and knowledge generation. Its integration into diverse sectors reflects its capacity to foster collaboration and address societal and organisational challenges. Adapting to AI's rapid evolution is crucial for businesses, employees, and governments navigating this dynamic landscape. Research limitations: This study relied on 2188 academic papers from the arXiv platform, centring its findings on academic contexts. Moreover, regional and cultural differences in AI adoption were not addressed. Future research should incorporate broader datasets and interdisciplinary approaches to provide a more comprehensive understanding of AI's global impact and socio-economic implications. Practical implications/applications to practice: Organisations can leverage AI to drive productivity, optimise processes, and create innovative solutions across industries. Strategic AI adoption requires investment in workforce reskilling and the ethical implementation of AI systems. Decision-makers must prioritise long-term planning to achieve AI's full potential while ensuring it supports both organisational competitiveness and sustainable development. Social implications/impact on society and/or policy: AI's rapid expansion highlights its potential to address societal challenges, from reducing inequities to fostering global development. However, pressing issues such as ethical use, algorithmic fairness, and data privacy demand urgent attention. Governments must establish equitable frameworks to ensure that AI supports inclusive progress and mitigates potential negative consequences, fostering sustainable societal progress. Originality/what is new about your research?: This study uniquely combines large-scale empirical evidence with theoretical perspectives to analyse AI adoption trends. It highlights AI's penetration into industries, organisational areas, and tasks, emphasising its progression beyond traditional applications to drive task-specific specialisation, reshape innovation processes, and expand the boundaries of knowledge creation. © 2025 Elsevier B.V., All rights reserved. | H56: Não | I56: Sim | J56: =IF(OR(ISBLANK(H56),ISBLANK(I56)),"",IF(H56<>I56,"Diferente","Igual")) -> Diferente | K56: Justification: title does not provide enough evidence that the study (i) investigates AI agents for organizational decision-making or process automation, (ii) targets customer service/decision support, and (iii) reports empirical/case evidence – at least one IC is not satisfied, so score = 0. | L56: Strong alignment with all inclusion criteria and no (relevant) exclusion criteria met. | M56: LLM 1 | N56: =IF(OR(ISBLANK(H56),ISBLANK(I56)),"", IF(J56="Diferente","Sim",IF(H56="Sim","Sim","Não"))) -> Sim
A57: Scopus | B57: Göndöcs, D.; Horváth, S.; Dӧrfler, V. | C57: Uncovering the dynamics of human-AI hybrid performance: A qualitative meta-analysis of empirical studies | D57: 2025 | F57: Human-AI collaboration is an increasingly important area of research as AI systems are integrated into everyday workflows and moving beyond mere automation and augmentation to more collaborative roles. However, existing research often overlooks the dynamics and performance aspects of this interaction. Our study addresses this gap through a review of empirical AI studies from 2018–2024, focusing on the key factors influencing human-AI collaboration outcomes within the spectrum of Human-Centered Artificial Intelligence (HCAI). We identify 24 critical performance factors that influence hybrid performance, grouped into four categories using thematic analysis. Then, we uncover and analyze the complex, non-linear interdependencies between these factors. We present these relationships in a factor dependency graph, highlighting the most influential nodes. The graph and specific factor interactions supported by the papers reveal a quite complex web, an interconnectedness of factors. As opposed to being an easy-to-predict combination of inputs, human-AI collaboration in a given context likely leads to a dynamic, evolving system with often non-linear effects on its hybrid performance. Our findings and the previous research on automation technologies suggest that the application of AI tools in collaborative scenarios would benefit from a comprehensive performance framework. Our study intends to contribute to this future line of research with this initial framework. © 2025 Elsevier B.V., All rights reserved. | G57: Engineering research; AI design; Empirical studies; Human-AI collaboration; Hybrid performance; Interconnectedness; Literature reviews; Meta-analysis; Performance; Performance factors; Qualitative meta-analyze; Factor analysis | H57: Não | I57: Não | J57: =IF(OR(ISBLANK(H57),ISBLANK(I57)),"",IF(H57<>I57,"Diferente","Igual")) -> Igual | K57: Justification: title does not provide enough evidence that the study (i) investigates AI agents for organizational decision-making or process automation, (ii) targets customer service/decision support, and (iii) reports empirical/case evidence – at least one IC is not satisfied, so score = 0. | L57: Fails IC 3 / Meets EC 5 (Type: article or identified as Review) | M57: LLM 2 | N57: =IF(OR(ISBLANK(H57),ISBLANK(I57)),"", IF(J57="Diferente","Sim",IF(H57="Sim","Sim","Não"))) -> Não
A58: Scopus | B58: Gao, J.; Opute, A.P.; Jawad, C.; Zhan, M. | C58: The influence of artificial intelligence chatbot problem solving on customers’ continued usage intention in e-commerce platforms: an expectation-confirmation model approach | D58: 2025 | F58: The rapid advancement of artificial intelligence (AI) technology has led to its widespread application across various fields, including e-commerce platforms. AI chatbots, powered by large data models, have emerged as a crucial tool for enhancing customer service and user experience. This study aims to investigate the impact of AI chatbot problem-solving capabilities on users’ intention to continue using these services within e-commerce platforms. By integrating elements from the Expectation-Confirmation Model (ECM) and the Technology Acceptance Model (TAM), a comprehensive research model is proposed to examine the relationships between problem-solving, confirmation, perceived ease of use, satisfaction, trust, and continued usage intention. The study employs structural equation modelling (SEM) to analyse data collected from 315 participants through an online questionnaire. The findings reveal that problem-solving abilities positively influence users’ confirmation, which in turn positively affects satisfaction, perceived ease of use, and trust. Furthermore, perceived ease of use exhibits a positive impact on satisfaction, trust, and continued usage intention. Satisfaction and trust have a positive impact on continued usage intention, with satisfaction showing a stronger influence than both problem-solving ability and ease of use. The study contributes to the theoretical understanding of user perceptions and behaviours in AI-driven interactions within e-commerce platforms. It highlights the importance of problem-solving capabilities, perceived ease of use, satisfaction, and trust in driving users’ continued engagement with AI chatbots. Practical implications for AI technology developers and e-commerce companies are discussed, emphasizing the need to focus on enhancing chatbots’ problem-solving proficiency and user-friendliness to foster long-term user retention. Future research directions are proposed, addressing the study's limitations and exploring the generalizability of the findings beyond the e-commerce context. © 2025 Elsevier B.V., All rights reserved. | H58: Não | I58: Sim | J58: =IF(OR(ISBLANK(H58),ISBLANK(I58)),"",IF(H58<>I58,"Diferente","Igual")) -> Diferente | K58: Justification: title explicitly mentions an AI chatbot / conversational agent in an organizational service context and implies empirical evaluation of its effect on customers or processes – satisfies IC1–IC4. | L58: Strong alignment with all inclusion criteria and no (relevant) exclusion criteria met. | M58: LLM 1 | N58: =IF(OR(ISBLANK(H58),ISBLANK(I58)),"", IF(J58="Diferente","Sim",IF(H58="Sim","Sim","Não"))) -> Sim | P58: Antonio
A59: Scopus | B59: Brachman, M.; El-Ashry, A.; Dugan, C.; Geyer, W. | C59: Current and Future Use of Large Language Models for Knowledge Work | D59: 2025 | F59: Large Language Models (LLMs) have introduced a paradigm shift in interaction with AI technology, enabling knowledge workers to complete tasks by specifying their desired outcome in natural language. LLMs have the potential to increase productivity and reduce tedious tasks in an unprecedented way. A systematic study of LLM adoption for work can provide insight into how LLMs can best support these workers. To explore knowledge workers' current and desired usage of LLMs, we ran a survey (n=216). Workers described tasks they already used LLMs for, like generating code or improving text, but imagined a future with LLMs integrated into their workflows and data. We ran a second survey (n=107) a year later that validated our initial findings and provides insight into up-to-date LLM use by knowledge workers. We discuss implications for adoption and design of generative AI technologies for knowledge work. © 2025 Elsevier B.V., All rights reserved. | G59: Human engineering; Information systems; Natural language processing systems; 'current; Adoption; AI Technologies; Knowledge work; Knowledge workers; Language model; Large language model; Natural languages; Paradigm shifts; Workers'; Knowledge organization | H59: Sim | I59: Não | J59: =IF(OR(ISBLANK(H59),ISBLANK(I59)),"",IF(H59<>I59,"Diferente","Igual")) -> Diferente | K59: Justification: title does not provide enough evidence that the study (i) investigates AI agents for organizational decision-making or process automation, (ii) targets customer service/decision support, and (iii) reports empirical/case evidence – at least one IC is not satisfied, so score = 0. | L59: Fails IC 2 (Does not address customer service, automation, or decision support) | M59: LLM 2 | N59: =IF(OR(ISBLANK(H59),ISBLANK(I59)),"", IF(J59="Diferente","Sim",IF(H59="Sim","Sim","Não"))) -> Sim
A60: Scopus | B60: Alfahid, A.; Lhioui, C.; Asklany, S.; Hamdaoui, R.; Hamdi, M.; Abbas, G.; Yousef, A.; Sahbani, A. | C60: Enhancing automated robotic services efficiency through intelligent dependent robotic computation | D60: 2025 | F60: This research focuses on enhancing the adaptability and efficacy of service robots in real-time, multi-scenario environments where diverse settings complicate the interpretation of user commands and dynamic environmental fluctuations. It introduces the Commuting Input Valuation Approach (CIVA), which combines transfer learning with a flexible state transfer system to improve robot response rates, minimize unnecessary actions, and enhance learning efficiency across varied environments. The main contributions are (i) a continuous training framework for robots, (ii) a method for sharing information between response and learning stages, (iii) transfer learning approaches suited for both short and long inputs, and (iv) an adaptive reaction rate calculation that accounts for real-time conditions. CIVA was evaluated on 32 interactive tasks using the Daily Interactive Robot Manipulation (DIM) dataset, containing 1,603 dependent and 1,751 independent commands. Performance was assessed relative to baseline robotic models utilizing criteria including task completion duration, input interpreting failure rate, command-to-action efficiency, reaction successful rate, and learning velocity. In a targeted screw-loosening assessment comprising 120 input commands over 70 seconds, CIVA demonstrated a 35% reduction in task completion duration, a 42% decline in interpretation errors, a 28% enhancement in instruction-to-action efficiency, a 45% augmentation in response success rate, and a 50% increase in learning velocity relative to baseline measurements. The findings indicate that CIVA can enhance human-robot interaction and task performance; nevertheless, additional validation is necessary to verify reproducibility and generalization across diverse real-world contexts. © 2025 Elsevier B.V., All rights reserved. | G60: algorithm; Article; artificial intelligence; automatic speech recognition; computer model; decision making; e-learning; evolutionary adaptation; knowledge; learning; nonhuman; robotic computation; training; transfer of learning; velocity; workflow | H60: Não | I60: Não | J60: =IF(OR(ISBLANK(H60),ISBLANK(I60)),"",IF(H60<>I60,"Diferente","Igual")) -> Igual | K60: Justification: focuses on service robots/consumer acceptance, not on AI agents (LLMs, chatbots, multi-agent or RL) applied to organizational decision-making or task automation (fails IC1/IC2). | L60: Fails IC 2 (Does not address customer service, automation, or decision support) | M60: LLM 2 | N60: =IF(OR(ISBLANK(H60),ISBLANK(I60)),"", IF(J60="Diferente","Sim",IF(H60="Sim","Sim","Não"))) -> Não
A61: Scopus | B61: Guo, X.; Wan, X. | C61: AI-driven nudges: Influence of chatbot personas on consumer food choices | D61: 2025 | F61: Customized chatbot personas can meet the personalized needs of consumers and enhance user engagement in human-chatbot interactions. We conducted a study to investigate the influence of interacting with a chatbot customized as a health coaching assistant versus a gourmet recommendation assistant on participants’ food choices. Participants were instructed to choose three dishes from a set of two meat and two vegetable options to compose a three-dish meal, both before and after they interacted with the health coaching assistant or the gourmet recommendation assistant. The results revealed a significant decrease in the frequency of meat-heavy meal selections after participants interacted with the health coaching assistant, compared to the gourmet recommendation assistant. These findings suggest that interacting with chatbots tailored as health coaching assistants can effectively nudge consumers toward more sustainable food choices. These findings highlight the potential of human-AI interactions in promoting sustainability and offer implications for the design and implementation of chatbots in the restaurant industry. © 2025 Elsevier B.V., All rights reserved. | G61: adult; Article; artificial intelligence; coaching; consumer; controlled study; decision making task; deep learning; female; food industry; food intake; food preference; healthy diet; human; human experiment; machine learning; male; meal; meat; natural language processing; normal human; restaurant; sex difference; software; task performance; vegetable; consumer attitude; decision making; generative artificial intelligence; middle aged; psychology; young adult; Adult; Choice Behavior; Consumer Behavior; Female; Food Preferences; Generative Artificial Intelligence; Humans; Male; Meals; Middle Aged; Restaurants; Young Adult | H61: Não | I61: Não | J61: =IF(OR(ISBLANK(H61),ISBLANK(I61)),"",IF(H61<>I61,"Diferente","Igual")) -> Igual | K61: Justification: title explicitly mentions an AI chatbot / conversational agent in an organizational service context and implies empirical evaluation of its effect on customers or processes – satisfies IC1–IC4. | L61: Fails IC 2 (Does not address customer service, automation, or decision support) | M61: LLM 2 | N61: =IF(OR(ISBLANK(H61),ISBLANK(I61)),"", IF(J61="Diferente","Sim",IF(H61="Sim","Sim","Não"))) -> Não
A62: Scopus | B62: Sestino, A.; Rizzo, C.; Irgang, L.; Stehlíková, B. | C62: Redesigning healthcare service delivery processes through medical chatbot integrations: balancing chatbot features and patients’ individual differences | D62: 2025 | F62: Purpose The utilization of virtual agents, particularly chatbots, within healthcare and medical contexts is witnessing exponential growth owing to their capacity to provide comprehensive support to patients throughout their healthcare journey, by reshaping the healthcare business processes. Such transformation in healthcare service delivery processes is enabled by those digital entities able to offer a preliminary screening and consultation platform, facilitating patients’ interactions with real medical professionals. However, when redesigning processes through the integration of new technologies, particular attention to the reactions of end users cannot be neglected. Thus, the purpose of this paper is investigating how both chatbots' features and patients' individual differences may shape a redesigned/renewed service in the healthcare sector. Design/methodology/approach Through two experimental studies (Study 1 and Study 2), we examined the impact of chatbot tone of voice (formal vs unformal) on patients’ behavioral responses, particularly their intention to use. Findings Our investigation shed light on chatbots’ characteristics in terms of perceived warmth, denoting the friendliness and empathy conveyed by the chatbot, and competence, reflecting its effectiveness in addressing user queries or tasks, when used to reshape the service delivery process; Moreover, we also shed light on the moderating role of emotional receptivity seeking, indicating that the emotionality and non-verbal communication between doctor and patient, cannot be overlooked even in innovative digital environments. Practical implications Managers and marketers could leverage insights from this study to tailor chatbot interactions, optimizing tone of voice to enhance patient engagement and satisfaction. By focusing on perceived warmth and competence, they can design more effective digital health solutions. Additionally, recognizing the role of emotional receptivity can guide strategies for integrating chatbots in a way that maintains a human touch in patient communications. Social implications Findings importantly underscore the relevance of chatbot in improving patient care, making digital interactions more empathetic and responsive. This relevance extends to business process management by demonstrating how integrating emotionally intelligent chatbots may contribute to better service delivery on the basis of personalized and effective healthcare experiences. Originality/value The originality of this paper is about the relevance of considering chatbots’ and final users’ characteristics to strategically plan healthcare services process redesign. Indeed, it examines chatbots' perceived warmth and competence in reshaping service delivery processes. Additionally, it highlights the moderating role of emotional receptivity seeking, emphasizing the importance of emotional communication in digital healthcare environments. © 2025 Elsevier B.V., All rights reserved. | H62: Sim | I62: Sim | J62: =IF(OR(ISBLANK(H62),ISBLANK(I62)),"",IF(H62<>I62,"Diferente","Igual")) -> Igual | K62: Justification: title explicitly mentions an AI chatbot / conversational agent in an organizational service context and implies empirical evaluation of its effect on customers or processes – satisfies IC1–IC4. | L62: Strong alignment with all inclusion criteria and no (relevant) exclusion criteria met. | M62: LLM 1 | N62: =IF(OR(ISBLANK(H62),ISBLANK(I62)),"", IF(J62="Diferente","Sim",IF(H62="Sim","Sim","Não"))) -> Sim
A63: Scopus | B63: Bandi, A.; Kongari, B.; Naguru, R.; Pasnoor, S.; Vilipala, S.V. | C63: The Rise of Agentic AI: A Review of Definitions, Frameworks, Architectures, Applications, Evaluation Metrics, and Challenges | D63: 2025 | F63: Agentic AI systems are a recently emerged and important approach that goes beyond traditional AI, generative AI, and autonomous systems by focusing on autonomy, adaptability, and goal-driven reasoning. This study provides a clear review of agentic AI systems by bringing together their definitions, frameworks, and architectures, and by comparing them with related areas like generative AI, autonomic computing, and multi-agent systems. To do this, we reviewed 143 primary studies on current LLM-based and non-LLM-driven agentic systems and examined how they support planning, memory, reflection, and goal pursuit. Furthermore, we classified architectural models, input–output mechanisms, and applications based on their task domains where agentic AI is applied, supported using tabular summaries that highlight real-world case studies. Evaluation metrics were classified as qualitative and quantitative measures, along with available testing methods of agentic AI systems to check the system’s performance and reliability. This study also highlights the main challenges and limitations of agentic AI, covering technical, architectural, coordination, ethical, and security issues. We organized the conceptual foundations, available tools, architectures, and evaluation metrics in this research, which defines a structured foundation for understanding and advancing agentic AI. These findings aim to help researchers and developers build better, clearer, and more adaptable systems that support responsible deployment in different domains. © 2025 Elsevier B.V., All rights reserved. | G63: Architecture; Autonomous agents; Intelligent agents; Memory architecture; Adaptive ai; Agentic ai; Ai agent; Ai framework and architecture; AI systems; Chatgpt; Ethical ai; Goal-directed; Goal-directed ai; Langchain; Metagpt; Multi agent; Multi agent systems | H63: Sim | I63: Não | J63: =IF(OR(ISBLANK(H63),ISBLANK(I63)),"",IF(H63<>I63,"Diferente","Igual")) -> Diferente | K63: Justification: secondary/SLR/agenda study – does not present primary empirical evidence of AI agent implementation in organizational customer service, process automation, or decision support (fails IC3). | L63: Fails IC 2 (Does not address customer service, automation, or decision support). Fails IC 3 / Meets EC 5 (Type: review or identified as Review) | M63: LLM 2 | N63: =IF(OR(ISBLANK(H63),ISBLANK(I63)),"", IF(J63="Diferente","Sim",IF(H63="Sim","Sim","Não"))) -> Sim
A64: Scopus | B64: Pukach, A.; Teslyuk, V.; Lysa, N.; Sikora, L.; Fedyna, B. | C64: Information-Cognitive Concept of Predicting Method for HCI Objects’ Perception Subjectivization Results Based on Impact Factors Analysis with Usage of Multilayer Perceptron ANN | D64: 2025 | F64: An information-cognitive concept of a predicting method for obtaining specialized human–computer interaction (HCI) objects’ perception subjectivization results, based on impact factors analysis, with the use of multilayer perceptron (MP) artificial neural networks (ANNs), has been developed. The main purpose of the developed method is to increase the level of intellectualization and automation of research into relevant processes of HCI objects’ perception subjectivization, especially in the context of software products’ comprehensive support processes. The method is based on the developed conceptual models and the developed mathematical model, as well as a specialized developed algorithm. Results prediction is carried out on the basis of a preliminary in-depth analysis of a set of unique direct chains (UDCs) of neurons of the relevant encapsulated MP ANN, built on the basis of researching the results of isolated influences of each of the previously declared impact factors and further comparing the present direct chain (of each separate investigated modeling case) with UDCs from the aforementioned sets. As an example of practical approbation of the developed method, the appropriate practically applied problem of identifying a member of the support team, whose multifactor portrait is as close as possible to the corresponding multifactor portrait of a given client’s user, has been resolved. © 2025 Elsevier B.V., All rights reserved. | G64: Chains; Factor analysis; Human computer interaction; Multilayers; Comprehensive software support; Computer interaction; Impact factor; Interaction object’ perception subjectivization; Multilayers perceptrons; Neural-networks; Object perception; Predicting method; Software support; Subjectivization result forecasting; Forecasting | H64: Não | I64: Sim | J64: =IF(OR(ISBLANK(H64),ISBLANK(I64)),"",IF(H64<>I64,"Diferente","Igual")) -> Diferente | K64: Justification: title does not provide enough evidence that the study (i) investigates AI agents for organizational decision-making or process automation, (ii) targets customer service/decision support, and (iii) reports empirical/case evidence – at least one IC is not satisfied, so score = 0. | L64: Strong alignment with all inclusion criteria and no (relevant) exclusion criteria met. | M64: LLM 1 | N64: =IF(OR(ISBLANK(H64),ISBLANK(I64)),"", IF(J64="Diferente","Sim",IF(H64="Sim","Sim","Não"))) -> Sim
A65: Scopus | B65: Rahim, M.A.; Rokonuzzaman, M.; Abu Alqumsan, A.A.; Arogbonlo, A.; Islam, M.Z.; Trinh, H.; Islam, M.S. | C65: An intelligent and secure internet of robotic things: A review and conceptual framework | D65: 2025 | F65: Robots are increasingly being deployed across various fields and applications, including agriculture, manufacturing, transportation, surveillance, and rescue missions. The integration of technologies such as Artificial Intelligence (AI) and the Internet of Things (IoT) with robotics significantly enhances their capabilities and expands their range of applications. Rapid advancements in these technologies have driven notable progress in robotics research, particularly in the domain of AI-enabled Internet of Robotic Things (IoRT). However, our extensive literature study finds that there is a growing need for the development of big data–enabled secure IoRT systems capable of handling vast amounts of data generated by large-scale heterogeneous, homogeneous robots and multiple stakeholders. Addressing this need is essential to meet modern industrial and societal demands. Therefore, this paper presents a conceptual framework for AI-enabled, big data analytics–driven secure and reliable IoRT, based on a comprehensive review of the literature. The framework emphasizes key enabling technologies, including connectivity, cloud and edge computing, big data analytics, and cybersecurity systems, with the ultimate aim of supporting the transition to Industry 5.0. Furthermore, we explore several promising research directions that could enhance the intelligence and security of future IoRT systems. Before concluding, we provide an in-depth discussion of the benefits, limitations, and challenges associated with IoRT. We hope this work will serve as a valuable resource for researchers and practitioners in advancing next-generation intelligent robotic systems for the betterment of society. © 2025 Elsevier B.V., All rights reserved. | H65: Não | I65: Não | J65: =IF(OR(ISBLANK(H65),ISBLANK(I65)),"",IF(H65<>I65,"Diferente","Igual")) -> Igual | K65: Justification: secondary/SLR/agenda study – does not present primary empirical evidence of AI agent implementation in organizational customer service, process automation, or decision support (fails IC3). | L65: Fails IC 2 (Does not address customer service, automation, or decision support). Fails IC 3 / Meets EC 5 (Type: review or identified as Review) | M65: LLM 2 | N65: =IF(OR(ISBLANK(H65),ISBLANK(I65)),"", IF(J65="Diferente","Sim",IF(H65="Sim","Sim","Não"))) -> Não
A66: Scopus | B66: Gursoy, D. | C66: Artificial intelligence (AI) technology, its applications and the use of AI powered devices in hospitality service experience creation and delivery | D66: 2025 | F66: The rapid advancement of artificial intelligence (AI) is transforming the hospitality industry, enhancing service delivery, customer experiences, and operational efficiency. AI-powered innovations such as generative AI, service robots, autonomous systems, and smart assistants are streamlining operations, personalizing guest interactions, and optimizing resource management. While AI's benefits for businesses and customers are well-documented, its broader impacts on employees, customer behavior, and ethical considerations remain underexplored. This special issue of the International Journal of Hospitality Management addresses these gaps by presenting cutting-edge research on AI applications in hospitality. The featured studies explore AI-driven customer engagement, workforce adaptation, service recovery, and sustainability. By highlighting emerging trends and evidence-based insights, this issue informs industry leaders, policymakers, and academics about AI's opportunities and challenges, emphasizing the need for a balanced approach between technological innovation and human-centric service excellence © 2025 Elsevier B.V., All rights reserved. | H66: Não | I66: Não | J66: =IF(OR(ISBLANK(H66),ISBLANK(I66)),"",IF(H66<>I66,"Diferente","Igual")) -> Igual | K66: Justification: title does not provide enough evidence that the study (i) investigates AI agents for organizational decision-making or process automation, (ii) targets customer service/decision support, and (iii) reports empirical/case evidence – at least one IC is not satisfied, so score = 0. | L66: Fails IC 3 / Meets EC 5 (Type: editorial or identified as Review) | M66: LLM 2 | N66: =IF(OR(ISBLANK(H66),ISBLANK(I66)),"", IF(J66="Diferente","Sim",IF(H66="Sim","Sim","Não"))) -> Não
A67: Scopus | B67: Matthews, M.J.; Su, R.; Yonish, L.; McClean, S.; Koopman, J.; Yam, K.C. | C67: A Review of Artificial Intelligence, Algorithms, and Robots Through the Lens of Stakeholder Theory | D67: 2025 | F67: With the arrival of the Fourth Industrial Revolution, intelligent machines are affecting the daily lives of multiple organizational stakeholders. However, despite the continued expansion of intelligent machines in society, management scholarship has generally lagged, and current frameworks are under-equipped to offer meaningful guidance regarding the intersection of intelligent machines and organizations. We address this issue via a multidisciplinary review and a novel framework of intelligent machines and value creation. First, we discuss the characteristics of intelligent machines (i.e., autonomy, learning, inscrutability, and materiality) and how variation in these characteristics impacts their affordances and, subsequently, the value offered to stakeholders. We also advance the notion of value contingencies, which captures the idea that the value afforded by intelligent machines is conditional and that stakeholders’ dispositions and exploitation of intelligent machines must be considered when assessing value creation. Building on our framework, we offer recommendations for future research. Overall, we forward the literature by showcasing how intelligent machines often create both advantages and disadvantages for stakeholders and demonstrate how practitioners, policymakers, and management scholars may consider this moving forward. © 2025 Elsevier B.V., All rights reserved. | H67: Não | I67: Não | J67: =IF(OR(ISBLANK(H67),ISBLANK(I67)),"",IF(H67<>I67,"Diferente","Igual")) -> Igual | K67: Justification: secondary/SLR/agenda study – does not present primary empirical evidence of AI agent implementation in organizational customer service, process automation, or decision support (fails IC3). | L67: Fails IC 2 (Does not address customer service, automation, or decision support). Fails IC 3 / Meets EC 5 (Type: review or identified as Review) | M67: LLM 2 | N67: =IF(OR(ISBLANK(H67),ISBLANK(I67)),"", IF(J67="Diferente","Sim",IF(H67="Sim","Sim","Não"))) -> Não
